verilog-workbench/src_new/accumulator.v
`default_nettype none
`timescale 1ns/1ns


module accumulator (
    input wire [1023:0] w_in,
    input wire [1023:0] spk_in,
    output reg [7:0] u_out
    ); 

    wire [1023:0] synapse;
    assign synapse = w_in & spk_in;

    integer i;
    always @(*) begin
        u_out = 0;
        for (i = 0; i<1024 ; i=i+1) begin
            if (u_out >= 255) begin
                u_out = 255;
            end else if (synapse[i] == 1) begin
                u_out = u_out + 1;
            end
                
        end
    end

    `ifdef COCOTB_SIM 
    initial begin
    $dumpfile ("accumulator.vcd");
    $dumpvars (0, accumulator);
    #1;
    end
    `endif

endmodule

verilog-workbench/accumulator.vcd
$date
	Fri Oct  7 00:39:20 2022
$end
$version
	Icarus Verilog
$end
$timescale
	1ps
$end
$scope module accumulator $end
$var wire 1024 ! spk_in [1023:0] $end
$var wire 1024 " synapse [1023:0] $end
$var wire 1024 # w_in [1023:0] $end
$var reg 8 $ u_out [7:0] $end
$var integer 32 % i [31:0] $end
$upscope $end
$enddefinitions $end
#0
$dumpvars
bx %
bx $
bz #
bx "
bz !
$end
#10000000
b10000000000 %
b11110010 $
b100100100000010010100000101010110110100000000100010101000000100110010010000101010001000000000000100100000000110000001101001111110000010100010000000000101000100000000010000000000010100001000010010100010000000000001000010100000000101010011000101001100000100000001000100010100010000100101100000000101000000100011001000000001001000100000100001100000110010101010010000100000000000001100100000011000010100100000000010000000001010111000000000010010001100000000000000000010000100000101000000100000000100001000110010010011000100000010010000001010100011000110010111001000000000001001000100110001100000000100000010001001011000000000001000011100000100000010000001100000000000011110100000000011110000000000000000000010001000011000000100000001111000000100000100000001110001011000000000100010000110001000010000000001001101000101000000000000000101001101000000101001000100001000010001100000000010000010000100101000000000010000000000000000100001001000001100010001001100000000000100000111010001000000000010001000000000000100010000000001000011 "
b1101100100100010010100111111011110110101000000100010101000011110110010011000101110001000101100000110110000000110000001101001111110101010110010010101010111001110000100011010000110010111001010011010100010000000001011100010100100011101011111000101101100010101001011010100010100010101110101100000001101000000110011001010010101011100110101100011100010111110101010011000101000001000101101100010011010110110101001110010101100101110111101000101010111111110001010000100000011001110100101100110110010010101001010110011110111001110100110010101001110110111000111010111011010010001101101001100110011100001110100101011001111011100010000101000011111000100100110011011101101011100011110101010010011110011110101000101000011001110011101001111001001111010100111101110110011111011111000000000100111110110001010011100000101011101101101100011011010100101101101000001101001100100001000010001111100000010000010001111111100000001110010100101000111110001101100011100110111001101000000010111000111010011110000100011011000001111101100010000110101011011 !
b100110111000110010111000101010110111110100110111111111001000101111111010000101011011011000001100100100111111111001001111101111110010111101111001010001101100100011000010100001001011100101000010110100010111010100101010010111001000111110011111101001111001110110001000110010101110000100101100101000101000100100011111101001011001010101000111001111100110010101010110101100111000011001100110100011001010100100000001010000001011011111010011010010010001100110000010010111010110100011101001000100101001100011001111010010011010100000011011000111011101011010110111111101001101100011011110110111101111110001101000110101001111001100010001111011100110101010010000001100000000011011110110101001011111000001000011000101110101000111000110100110101111101010100010100001001110001011110111101110010001110001001110000010011001111000111011000000101010111011111001000101011011111011010010001100010111111100111110100101000010010010001011000010000101001011001001101011001101110001110000100110111110101000000000110101110000000010101111111001001100011 #
#20000000
b10000000000 %
b11111111 $
b1001100001001110001011000010010000001000100000010100000100100010110000000000000000100010111100000001010000000000101101100010100001000000000000100001100101100001010100110000001100110010010000101011000000100001000010011010000000100100000101100010100100000001000000010100100000000000101000000000110001000010101000100100101000111000000000011101100000000000100010000000011000000000000111100000010001000111100100010010100111001000010101011000000000001000010010010000101001000000000110000001010001000011000010111010010010001100000000000000010000100000100011000010001101000000010000001101111100010001000100010000000010001001000010100001100110000000000100000101001011100010000001000100000010100001000010000000000010000100000000000001110000000001000000000000100000110000111011000000010010000100000000000100000100101011011010010000110001100010100010010000010001000001101000100010110010011010000100001000000010000000011001001001000000000000001110000101000000001011000001100100010001000101000101000010100011000100000000010001110000000000 "
b1101100101001111001111001010010000101001110010011101110101110110110100000100000100100111111101100001010100001000111101100010101111100010010000100111100101100001010100110000011110111011010110101011101010110111000010011010010100100100100111101010101100000111100000011111101010000101101111001000110011000011101101100100101010111000001100111111101011000000100010000101111000000001001111110100110001101111110111010010101111001000010101011000101110011101011111110000101001001001000110100011011001001111100011111010010111111100010000101000011110100000100111100010101101011100010100011111111100110001100100111101000010101001010010100001100110001000010100100101001111101011001011100101111010110101011010010101001010000101110111010011110101101001011000010001100101110100111011001000110110000100000011001100000111101111111110010001110011100010100010010011011001000111101100100110110111111110000100001000011110011001011001101011001000100010111110000101010010011011110001111100111001000101000111101011100111011101001001011011110000000000 !
b1011101011001110101011010110010110011010100100010110001100101010111001110000011011111010111110000101110001110100101101100110100001010001101111111001110111111011011101110010101101110110011000111011010001101001010111011010101011111100000101100010100100111001010101110100100101000000101000100010110001101010111010110110111000111001100010011101100000100001101011101000011100010110110111101010011111000111101100110010100111111100110111011000010000101010110010011000111001100100011110010101110001100011010110111110011010001101000010010110110000110000101011000011001101000010110000101101111100011101001110010010110010001101101010111101110111000100001111000111011011100110100001010100000111101011100111000000000010111110000000000101110010010011100111001000111010110010111011000010010011010111001100100111000100101011011010011110111001100110110111011100010011100001111011111010111010011010100111111000000010100000011111001101100010001101001111011111100101101011000101100101010101010101100101000110111011000100010000110101110111100110 #
#30000000
b10000000000 %
b11111100 $
b10000000000111110010000000100010000000000001000010100100001000000100101000001010000001010101011010000001100100011010110000010000000001000100001000000000010110001000000000110100100111101010000010000000000000110000000001000000010000100001000100010000000000110100000001100100000100011000010001001100100000001000110010001000110110001010010000010101100000000000000110100000110100000100000010010000000001000000000100100000010000101000100000000000100010010010101010000000010000010010100010000110000100000000110111100110110000001010000000000101000000010001010110011001000100000001111010011101010000010000110011000011001011000010000011000000010010000000000011110000000000001001000111010100000101001000000100000010010010000001001000001100000000010001000100010001000100100000010000010100000011010010000011000100010000000010001000001001000000000000001101010000000000000100000000000000000111100010000000000000000101000010010000001010100000001000011000001000101001000000000010000001000000100000000001000010000011100000001001001000000111 "
b111010111110111111011110001100110001000010001010011100100101101110100111101001011000001010101011010100101100111011010111011010110011001000110001110000001111110011101110100110100110111101110000010000101000000111101010011001100010110100101101110111001010011110101000001100110001100111010111101111101101000101000110010001110110111101011010000110101100001100101011110101100110100110110000010010110100001100000001100110000010110101110100110000101110010011010111011110100110001010011110111010110101110100001110111100111110011001011000011010101000000011101111110111001110101000001111111111111010010110000111111100111001011101110000011001010010010000011010111110000010100001001100111011101000101011001000110100010011010101011001011011100101000110111000101111011000110100111111110010110010111010010000011010111010100100010111010001011010111001001111101010100101011000101000110010011110111100011010101010010100101000011110001001110100111101010011100001110101101110111010010000011000000111000110101000010110011110000001111001110000111 !
b1010001000001111110010000010110011110010001001001110110101011000001110101000111010110001110111111110000011100100011010110000111001000001010100011001110000010111001010000010110100101111111010010010011000100001110010100001100011010001101001000100010000100100111100011011110101100110011100010011001100100100011110111010101000110110011110110011010101100100001000000110110011110101001100010111110000010111011101000110100110011001111000101001000010100010010110101010000011010000110110101010001111000100011010111111101110110100101110001100101101001111110001010110011011001100000101111010011101111100010100110011001011001111000010111011010001011011110000101011111110100001011111001111110100100101001000010101010111110110000101001000101101010000010001101100010101101100101000010001110101001011111111001011001100111010011010001101111001001000100010001101011001010100001110101001100100000111100110101000101000000101010110011010111010111000001100111001101000111011000000000010100101111100100111000011010011001011101001111001101000001111 #
#40000000
b10000000000 %
b11010100 $
b100000001000000010100000000010000100000001001011000000000010000001000001000001001000000000000000100000100000000000000001000000000000000101000010000000000010100011000000101010000000001100000100101000000100001000000000100000000010001101000000000100000011001000001000000100011000000100010000000010000111001000000100000111110100000000100000000001000100101000000000110010000000100000010000100000001000001010010100000000000000100100010100001001001010100000000000000100010000010000000000001000000101010001010110100001010001010000000100000101000100110001010011000000000000000000000000010000100000000100101000010000010000000010100010000100001000000110000001100101010001000001000000110100000000011001010000000000000010000001010001101001100010001000000001000100100000101010000100000100000000100000000010011000001000010000000010000010110100100001100001000000000000000000000000000000000000010001010000000110011010000100001010000001000000110010011001100001010000000100000100101110010010000000001110000000101000100100000100000001 "
b100111000110001001000010010100100001010000101000011001011000001000011100011011011001001001011011110001001101000110001110000010101000001001000000101001010010011000010100111001000101010101000001111000101101000000100101100101101110001000111101101000101001100100011101000001111000110111001101101010010101110111111001110001111010111110110000010110000001001100110101100000000110110010001100111010110100100001001001010111101000001000111101100111110011001001010100000001000000100110000011000011001011001110101010011111110111001011001010010101100000101100111111111111011011110000001001010100010010010100010000100111011010000011010100110100010001101001011000111000001100101010101001011000000110111110010011111011010100100100010001001011111111001100110101101001001000101100100111011001111110110111000100111101110111000001010111011010010110110111101100001100101110101000110000101110111000110011001011001110000010110111010000100101110001001000000110010011001111001111100110101010100101111010011010001101110011000111010101100000101001011 !
b1010000000100010111000101111111001100111100110110101001111100100110010010101100101010011011100000000100100100101101110001001101011011100100010111101110011101000010011111011100100111111010010111100000100111011100110011000010010100010101010001111000000100101010011011100011000010101011110010110011000010010000111101000010100000111110101000001100000010111011101101001011100111010000010111000110001100001011010011111010100110000100000100100010101001101001111111011100101011101011011010010000100001000001101010101010111100001010111011100000111010111010100110001010111100000000000000100011000110001100101011111101100010100110100000011110011000110111000100110001111101111111011000001010001110100000101111001110001000011001010010011110001101101100011011000000011111100111010101010100100001100000010100000010010011100001001010100101110001011110110100001100001001010000001110000001000011000000100110001010110100110011010101110011010100011100010111110111011100101010010000100100101101110111010001010001110100101101100110110010110000001 #
#50000000
b10000000000 %
b11111111 $
b10100100001100000000000000000110001010001000010000111000000000110000010010011000100001000110100000001010000010001101000000010001010100010101010000001000101000000001000001110000100010000101000000000000000000110110011000000000010101101010101000110001000000001000001001000000010001000000010000000101100111000110000000100100100000001001101011000000010000100110110000000110001001001100010001100010100000000001001101010000000000000100000100100010100001000100111100001001111010000001101000001000000110110000001010000010000001101100001000101001001001010000001010000010000100011100100000000000101000010000100111001010010000000100110000100100000010000110001001011101000010011000000000000100100000100000001000000000010000000100100000101011000011100000000000000010100000001000001010000010010001100100000101110010000000010101000001000001101001000000010100100000101001000101001000110000100000000100001000000010000001000001110000001001000100010000100101000000000001100101011000010010001010000010000010000001000110001000000000000000010000 "
b1111110110011101000010000010110110001010001010011001111001000101110000010011011000101001000110110010101010100111011101000011010001110110010111011001001101101101000001110101110101110110001101100110010000010010110110011001010000111101111111111010111001000001001010001111111011110011101001011010011101110111001111000000111110101111001011111011100001111000110110111100010110111101011100111101100010101101001111101101010100110101100101000101110110111111001100111100001001111010000101101100011010000110111001101110011011010111111111001000111001101001010010101111010110001100111100111001010000111001110000111111011110110100100101110100101100000111001111001001111111000010011000010010010111110110100000001000000000110100000101100001101011010011100001100111100111101101001010001010110111010101101100100111110011111001110101000111010001101101110010010111100100111101100111011011110000110111000101111101000010010101010001111010001001011100010000101101110010000001101101011011010010111010100010010111111011010110001010000100000000110000 !
b10100101101110011000110101001111011111101100110110111110010010111000111010011110100011010110101100001011010010101111010000011011011101011101110000101000111010101101000001110010100011110101011000001110001101111110111000101001010111101010101100110101011100001101001001000100010101000010010101100101100111100110000010100101100000101101101011010100010100100110110010000110001001101111010011111111110000100001011101011011001000010100110100100010100001010101111101111001111111000001111000001000110110110010011011000110101001101100001011101101001001111101011010100010110101011101100100100110101010010001100111001011010011011100110010100110101010010110101111011101001011011010101000100100100000101101111011101110010001011100100100101111100111100100001000010010110000001101101011001010110011110101000101111110000110011101000001100011111011000100111100110001101011001101001100111001101000001110001000000010000011101101110101101111100101010000110101001100001101100101011000011011001111011010001010000001001111011101101000100100010110 #
#60000000
b10000000000 %
b11111101 $
b1100001000010010000100010010010001000001001000001000100001100000101000000000001000000010000001101000000000000001010001100110100000000010000010000001100000000010000110100110001100100100010000011000000000000000000000100110000001000000010000110001101101001000100000010001001000100100100000010000100000000000101010010000010011001011100000000011000101000000100001000110100100101001000000011010011000011010010000001000001011000000110010000001000000000100100000010100000000000101110100000100001010100010010000101000000001110000000101000110000000001001000110000011010100011100010001001000010000010000001010011001000000100000000100101010011010000110000000010010000000000010000110000000011110010100000011001001000000000010100011000100000010000000001001000000000100111000000000000010111000100001000010100100010010000000001010000000000110000011001100100000100000000000110001001010110000000010000000001000000100111000100000000000000000000000001000001000100010100100100100000001001010010000000000101001000110001000100010110000110000000011 "
b1100011110110010100100111010011011000001001110001000101101111000101110111000001110001010000001101100000101110011010011100110100111111010000010001001100000001010001110110111001101110101010111011100000000010001010100100110000001100100010010110001101101001101110000010001001110111110111100110001111101100101111010111000010011001011100100010011010111001101111101000110101110101001111101111010011000111010010001001000001011001100110110001001010100011100100100011110110000000101110100100101011010110010110111111000000001110000011111100110100101001001111110100011010101011101010001011000110000010001011010011001001001101000110110101010011110000110110001011011011101100111000110001000011110010110000111001011100111000010101011100111100011100000111101010100101100111000000001101010111000110101011010100100011010000000001011100010001111001011011100100100110010010011110001101010111010100010011010001001110100111000100000011001100010000000101000001100100011110101101100000101101010011011001000111101000110011000100011110000110001100111 !
b1111001001011010000101010010110001100101111001001100110011100101111000000100101001010110010101101011000000000001111101110110111000000011111011010001110010000010000110101110111100100110011000011000111010100110000001111111100101010000010000111011101111101010100001011011101001100101100001011110100000001000101111010000010011001011100011101111101101010010100011001111110100101101000010011011011000011010110000001111101011100010111010010111101001000100111010110101000010001101111110010100001010101011010000101111010101110000100101001110010010001111000110001111111110011110111001001001010001111000101111011101110000100010001101111010011010010111001010010010000000001010011110010000011111110101111011011001001000111111110011000100011110000101001011000010010101111001000010000111111111100001000110111100010110000100111010001101110110100011001101101011101000101100111101011011110000010011000001001100000101111001110110000110010001110001001011001010100110101110100110110001011110110100010000101011111110101101110110110101111100011011 #
#70000000
b10000000000 %
b11111111 $
b1100100001101000010010000000000110000000011000001100000100001100101000011000001000101101000101000011000000100001100101100110100000100000000010001100100100010001011010000000000110001110010100010001000000000011000001100100000100110111010000011000101000000000100000100001100000001010000000001011000000010110000001001010000000100100110000010001000001100000000100011000110000000000010100001000010000100000000000000101011000010000001000100010001000000011010000100001101111000001011000000011011010001000000100000010101101000000000010000100001000100000000000100100000000000110000000101100010010000000000101000100110000011000001100011000001100010000100111111010010010110000010000001000000100000000101001000101000101000000111001110000001000010010110000000100000010110000000000010001000010000101100010010000001011100000000001000010000000010000001001000110000100001000000001000011010110000000011000101000000100000000001011101000010000000010100000100000000110000000010100000000001000100100010000001000000000001000000000011000100010010010 "
b1111100011101100110111100010010110010010111000011100111100001100111000011010101011111101000101001111110000101011100101100111101100100000100010101100100110010001011010010100110110001110011111010101000011000011001111110110100110110111010000011011111000011000110000110001101100111110000000111011100000011111001101001110000000100101111100010001011011101010000110111010110001100010110101001100010000100001111000001101011010111101001000110110001000110011010000100011111111101001111010001111111011001001101100001011111101010001000010000100101001100000000000101100010010001110111011101110111111000000000111101100111001111001111110011101001111110101100111111111010010110000111100001101100100000101111001100101000111010000111001110101101000110010111110000100110110110101111010011001010010001101101011010001011111110101000011011010101000111110111101000110000100001010001001000111011110010110011000111000100101000110011011101001110111000110100100101001000110100011011100000010101000101110011000001110100000101000001001111100110010011110 !
b1100111101111010011010000000101111001100011000001110000110001101101011011001001000101111000101100011001011100101110111111110110000100001010110011100111100111011011011000011000110101110110100011001111100010111100001101100011101111111011101011000101000100110100000100111100011001010101010001111001111110110110011001010101100110100110011111111100001110001100100011001111010000001011100011000011011100100000010110101111100010010111011101011101111000111011110110101101111000011011101000011011110101000010100010110101101000100111110101100011010100010010101110111100000000111000100111101010010101010011101000100110010011010001101011010111100011010101111111010110011110100010000101000010100001000101011010101010101000111111011110010001111010011110000001100000011111000000100010011001010000101110010011110001011101010101001100011000100010000001001100110110111101101010111110011010110000001011001101101001110001000101011111110011000110011101010100000001111000100110100011000011111100101110000001000011110001100000000011010100111110010 #
#80000000
b10000000000 %
b11111111 $
b1101001100000000000001000011011001100001010001110000000001011001000001001000000000110000000011010100000010000000101010010001010000010000000001000000010111110000001101000011100010000001000101000100000000001110001011011001000001100000010000000010000110100000100110000000100111000110000001000000000000000010100000100010000000100101001001100001000011010010000000000100000011000000000010101100000000011000000010100000100100000101010100010010100000000110001100001000100000101000000100111100100010010000000000100001001011001000000010001011000000010000010100001100101010010100010000110101000010100000000000000001100000111000000000100010001111000001100010010011100100011010000001010000100100000100001100000101010000000011010010110010010100100001100000010000000001000001000000010000010100000010001001000001100101000010010110000000000000000001001011101010010000100001010000000010100000110011101000001000000000010101110000001000000000110001100101010000000100000000000000100011000000100010000110000000100010111000100100000001000010111 "
b1011101101111110001001011010011011001110001110001111000011011011101100101001000000101111000100111010111100110010000111010011011011000010000000011010011010111110001001101001111110010001111010101011100000110111111001111011001010011111101110010001111001111110000100111100000100111100110011001000000011010011110101001111010000100100101111011100101001011010110000000000100000011111010110110101101000010111000000110100001110100011101010100110010100111000110001101111100110100111000100100111101100010010000000000101001001111001110111010101011110001011010111110011100101110110100111010110101110110100010101000000001110001111000010000100110101111010001110010011111100100011010110001010010100100000100001101000111110111011011010010110010011101110011101010010100001101110001101101010101110111000111011001000001100101100011010110110001101110101101011011111010011110110101010001011110101000110111101000011000001000011101110110101001110100111011100111010101000110100000101101100111000100100010100110000100101010111101110101000001110011111 !
b101101001100001100010101001011111101101101010111110011000101111001001011011001110010110010011011010100010010000100101011110001110011110101001101100000111111110000111101000011100010100001000101100111001000001110101011011011000101100000011001110010110110101100101110011101110111001110100111010010100000100011110100100010110011100101001001110011110111111010111101011101111111000100000011101100100001011011000011100110101101100101111110011110111000011111011100001010100001101101010100111110111110111010101010110101111011101001000011001011001110110001010100101110101011011111010000111111000011111000010001111011100000111010101001100011001111000001100110110011111100011010001111010001111111100100011100010101011000000111011110110111010100100101100101010011000011000101000010011010011100110010101011000011101111010110111110001110000000010011001111101111110000101011011000100010100000111011111011101001110110010111110000001100000011110001100101110000100101001000000000100011100001111010001111010011110111111000100110001101001010111 #
#90000000
b10000000000 %
b11111111 $
b1000000000111010001001010100001101000011000110011100000000001010100000001000010110001000001000000010010010011101100000010000010000000011000001001100000000000000000110000000010100101000100101001000000000010010000000000010110000000001101000011100000000000100000100000000001000100001000010000000000000100010000100000000011000101101010100110100101101011110000000110100010110000001000000001010000011000010100000101001011000010001010010100100110001001100000110100001001010101110011010000110000001000001001001100100100100000100000101000100100110011000001000100100001000000100001110010000100000000000010000111011010000000000001001011001000001000011001100000001111111011111100100000000011000001000000000000011000000000000000100100000000000101001001000010010010010000000000110000001100110000000010000000000000000000101100001100100000001000010000001001010111010000001000011001000100000010000000000011000100100000001100010110000010100011000000000101000010000000101111100101000000001000100000010001000000001010000011010010011001 "
b1000001001001000100111010011001010101101101111011000110011100100001001010100010011000111110001000001000000011011010111101101100011001110010100111000001001101001111000111100110001000010110101000100101111000010100110111100000100010111110101011101100011101000000001100001101011000101000100001110010010110111011100110000101000000111001101101010100111100111101011110101000111111010110010101000001011011100111010011100100101001111100010001010011100100111001011110001111100001011011101111111010010110010011111001101011101101100111101100100101001100111110011100011000110101011100000110001110110101111010000001010001111011110000011010101001011001010001001011001100111001111111011111100100000100111011111011100010110011010100100001001100100000000100101001111001010010111110111101010110100001110110000100010000110001111001000101100011100110100011001010010111001110111011000101011011101000100001111100000110111100110100000001110010110001011110011111000110111001011100001111111101101000110011001100010011001000001001110100011010110011001 !
b110110001100100011111110101101011110001111000011110111111101000010011111110101101111010110011011011111111010110010011111100010010110011001011011101111011100000000100000011110000110011100101001111101001100001011010010000101001011110001010101111011011100001101000110000100100111001110100001001111101001000100101010011110010101011110101111110110110100101101111111010000110100110111101011110110001010000011001010100011111011011001110101110110101101110101001100000110111101001010101110011010100110001001000001001001110100100100000100010111010110100110011001001110100110101001101101101110010000100100100000010010111111010001100100011101011111000111110011011110000101111111011111111111000001011100001100000000000011101011001010110111100111111000101011001100111111010011000000000110011111101111001010110010000110000010100111100101110101010001100010100001101011111010010001100011011110110010010001111001011001100100100111101011111000010100011000110001101000010001100101111110111000000101000111101010001100100011010000011111011111101 #
#100000000
b10000000000 %
b11111001 $
b1000000010000001000001101010010010100000001000110100001001000010000000000001000000000001010000101011000010010010000001001000010000001100100100001000100010100100000000010001001000100000001010101001000000000101000010001000010000100010000100000100010000001000010000110010000100000010100001000000001100000001001000001001000101010010001000100000010001100000001110000010101011011001110000110010110000001010100100011000000010000010010000000101000000100000001100100000010010000100000001000000000010000100000010110000001001000000100000000010000010010101000100000010010100000000100000010110100011000100010000000100000000000000000101000000100101100000000111011000000100000001000010001100000000001000010000000111000001000011001100011000111000000000111011000000010000000000000010010001101001010010001000110101000000001000000000001100111100001001000001000011000000110000010000010001000000000000000010000000110010001100001000010000100001000100000000000101010000000000000101001000101101100000001110010101001000100000001000000100111000001 "
b1001011011011100111101011111011111110110000111000111100001101100110001100011001101110000101110001101011110110011110001001101001011101011101111101001010100110110100011000110011001000101011011110111011000011000111110011011000110100101010000110100100110101001001110101110110011100000110100011010000101100001001001001001101100101010010111001100001010001111011111111101110101111011001110010111110110010001011110100011010001111110011110000011101000000100100001100101001011011011100010101001010010010100110100010111001101001100000100100100110000011011101110100011110010100101100101111110110101111001101010000000110101010001000100111010110100101101100000111011100011100000001000011001100111000001100010010000111110101000011101100111001111001001011111011100001011000000000010011010101111101011010001000110101000100011010100000001100111101001001001101100011000001110000010011110001110010000101000111000001110111011101111001010001101011100100010110000101010100101010000101111011101101100111001111011101011001101010001010000110111011001 !
b1000100010001001010001101110010010100101001111110110011011000010100001000001000001111001011100101111001011110011000001001110010010001110100100111000110010101111100110011101111101100100001010101001000100111101000010101110011010100111011101001101010000011010011010110010100110100011100001001111001100100001001000001011000111010110001000100000011011100100001110010011101011111011111101110011110100111010100110011100110010001110010100100101000010110000101111100100110110000100001001010001001111001100011011110010011011000000101000001010110010110101000100100010111100000001100000011111100011110110111110100101000101100100001101100001100101110001111111111001100110111011001010011110000100101001011001010111001011100111011100011010111000010100111111000110110010111110101010010001101001110111001011111111010011101101000101011100111110011011100011011111000110111000111000011111001101101000010010001110110010101110001100111110110101011111100001110101110010000100010101001000101101100000011110110111101100110101011000101100111100111 #
#110000000
b10000000000 %
b11111110 $
b10001000000011000010001110100010000010001111001000000000100000000000101000110000010001100110000000100110000001000001011101001100000010100000000100001000000000000000001011101010100010000010010000001001001101010000000000100001110110011000101100111000000100010001010010010010100001000000000110100101100000011101000000001000000100001000010010010000010000000000000100100000000010100010000101100011000110000000001010000100010001001001000110010000001000100110110001000001000001001001000000000000000000001011000100010000100001010100000001000110101100101000101000100000000100000010101100010010010010001100001000000010000000000010000000010001100001010100001000001100001011101000001000000010000000100110000010000001000000000101000100100000000000000010100100000001010000000110000001001001001110011100010000000000001000000000000110000000000011010000010100100100110001001000000011010100100110000000000001000000000000000001001000000010000100110010000000011000000001000001000000000001010011001110000000111000001010000000000000001000011000 "
b110001000100011110110001110100110110110001111001010001000100001000011111010111101011101100110001000100111000111100001011111001100101110101010001100001000001001011100001011111110100010000010110101101101011101010000000000110011110110011001111110111000001101011001010010110110100011011000100111110101110010011101000110001010101110001001110111010101010110010101000100110010100011100111011101100111001110101000011010100101011001011011011110010000011100100111110011001001100001011011011000101011100100001011011100010100101001111100000011011110101111111001101010111101001111110011101100011110111110101101101000001110000110100011001011011101111101011110001011011110111011101110001000110111000000111110000011010011000010100101000100111110001011101010100101000101110000000111000001011011011110011101010100011110011001001000010111001011110011110001110100100100110101001010000011011110100110011100100001000000000001100011011000010011010110110111010001011001101001001001101000001101010111101111100111111000111110110001000111011111011110 !
b1010011011010011001010001110110011001011011111111001010011110100001000101101110000010001111110000111100110001001010111111101001110000010110000100110011101010010000000111111101010110110010011011010001011001111111111001111101001111111011010101101111100110110110001111011010011110101000001001110101101100000111101100000001100010100101110011010010000010000000000110100101001001010100010100111101011110111010111101110001110110001001101100111111001001010110110111101000111010011001001000100010000011011001011100111011011100011010111111101000110101100101100101100100010110100001010101111010011010010001110001111000010001001011110010100110011100001110100111000101101001111101000111101001010011011100111010010100101111100010111101100100001010100010011101100111011011110110110101011001001001111011100111010000001101010010001000110100100001011010100010110111111111011101001000111010100111110000001000101001111001110000101001110001010101101111010000110011010000011100001000011010001110011001110001000111100001010001000110000101000011001 #
#120000000
b10000000000 %
b11111111 $
b1101101111000001000111000001101100010000001000000101101100001000000000011010001000110001000000000000000000001000000001011000101011001010000000100000010000000011100000000011000100001000000011001000000010000001010011010001001010000100000010110010011001011010000100110000100000000000001100000100010100000101000001000000000101110000101010001000010110010001000001101001100100000011100010000100110000000000010000110000110110001010000000010010011011010000100000000000100010011000000000100001000000110000001000000000011000111101100000001010001000001000000001001000001100011111100100000000000010000010000000000101001010101010010001001000000000100011110000000110010000000000010000000110001000000010101110001100100011100110100100111010100011000000000000000000000000010000100000100001000111010101010001101000010000000000001001000101011000001010100000000100101000100001100010110001111100100101001000001001011000010000000000000000100000100001000001000000000100100000000000000000000000110000001000001000010001001001000100000100011100001001 "
b1101101111100001001111000011111110111010001001011101101100001100110010111111101100111101001110100000010111001100000101011001101111001010110000110010010000000111111000001111001100011100010011001100000111010001010111110101111010010101010010110010011101111010100100111100110001100000001110000100010101110101001101101000111101111010101010101010010111010101110001101111100111001111110010101100110101100100010111110110110110101010001100010110011011110011100001101000110010111000001000100101001010111001001000111110011101111111100111111011001011001001010101101010101100111111110101010010100010100110011000101111101011101011010001001000000000110111110100010110011010000111111010100110111001100110101111001100101011100110100100111010100011001100000000010011010001010001100101110101000111011101010111111111010011001000011001000111011000001010100100000110101110100001101110111011111110111101101100101011011000010001101000101100101111100001000111110000000100101100110101000100000100111000101110111110011101001101010101001111111100101101 !
b1101111111001101110111100101101101010000001000100111101101111010000101011010011001110011010001011100001000101001100011011010101011011110001000101101110000010011100001010011110101101010000111001001010010100001111011010001001010101110001110111011011011011011010110110010100100001100011100000111011110001111100001010011000101110101111010011100011110010001000111101001111100110011101111010101110000000001010000110001111110001010110001111011011111011000110100000111101011011010110010100001100001110100101011000000111010111101110000001110111000001010000001011001001100011111100110101101010011011010100000010101001010101010010101111011101110100011111010101110110001100000010000001110001000001010111110101110100011110110110100111111100011110001011011001100001000111100100010100011011111110111010001101000110000100000101101101101011001011010111010110100101000111011110011110001111101100111011000011101111101111000000000000000110000110111011001000111010111100010000010000000010000110100001001001000110001001011000100110100011110011001 #
#130000000
b10000000000 %
b11111010 $
b1010101010000111010000000010100001100000100001100001010000000001001100001101001000000000000000011100000001100000010010001001000000000000110000100100100110100100011001100101000101001100111000000010000000000100000000000000000000000000000000000000001000100101000010101000010000100100000000000000000000100010010011100000000100100011011000000000001000001000000100000101000000000101000001001000100100011000000100000001000001110000101100000000000000001001000100100001000000000100000000000100000000000011001011111000001110100100110100001100000001000000010101000000000100011000000010101100000000000000110000100000010000000001000000110000010000011000011010100001100001100101000010010000100000110010001001101000010100100100000111010000100010010101110001110000110000011001011011001000000010010000100000000000010000000000000010111110000011010100000000000000000011100100000100000101010110000001000000010000001000000000010000010000100100000000100000000000000010000001011001000111010101000000000011000100000010100000011000010110000000100100 "
b1110101111001111110100000010100101101000100101110001010000001011001100101111011010000100110100011110010001100100010010011011000010001101110000100110101110101100011001100111001111011100111010000010000000010110000000100001011000011110001010000100101000100101011010111010011000110100001000101011011000100011110011100100001100111011011000101001001000001000000101100111000001100101100101011110100101011011010100010001110001110001101100000000011000001111000101100011000101101100010100000110101001110011011011111000011111100110110100101100000011100001010101010100001100111111000011101101010000011101111100110011110000000111001101111101110011111110011110101001111101100101011111011000110000110011101011101000011101100101000111110000100010110111111001111000110001111001011111001110000111010001110001100000010000110001001111111110000011110101011101100000000011100111100101100111111111000101001010010000001000101010010011111000100100000000101011100010000010000011111001010111010111101011100111101111110110100010111001010110101100110101 !
b1011111010000111011010011011110001110101111001100001111011000001101110001101101101010010001001011100001001100010011111101101011101110000111100111100100111100101011111100101000101001100111000000011101100000100011110000110000100100001010001011011001000110111100110101101010110100100010000000100000110110010011011111011100100100111111111010010111101111110100100010101111010010111010001001000111110011100100111101001000101111110101111010000000010101001011100111101011010000111000000000101010100000111001011111010101110100101111111011101000101001010011111000000100101011000000110101100101010100000110001100100010001101001000010110010010000011000111010110111100001100111000010110011100111111010011101101011010110101110000111010110100010010101110101110011111010011011011011101001100010111110101110000100110100000110000010111111001011010110000000010000111011101100001110000101010110100011100001011010001011010001110100010100110110100001110000010001110110000001011011101111010101010100010011000100000010101101011110010111000001100110 #
