verilog-workbench/src/control_unit_256.v
`default_nettype none
`timescale 1ns/1ns

`define STATE_INIT               4'd0
`define STATE_INPUT_O            4'd1
`define STATE_PRE_INPUT          4'd2
`define STATE_INPUT              4'd3
`define STATE_P_H                4'd4
`define STATE_HIDDEN             4'd5
`define STATE_PRE_OUTPUT         4'd6
`define STATE_OUTPUT             4'd7

module control_unit_256 (
    // w sram addr
    output reg [10:0] w_read_sram_addr,                 // w read

    // neuron selector
    output reg [5:0] cntrl_u_out_select,                // potential write
    output reg cntrl_spk_select,                        // input layer
    output reg [5:0] cntrl_u_in_select,                 // potential read

    // accumlators
    output reg cntrl_ac_reset,                          // reset ac when changing layers
    output reg cntrl_ac_oen,                            // read ac into the neuron when ready

    //neurons
    output reg cntrl_neu_reset,                         // reset neurons (on reset) (prob useless)

    //spk procssor
    output reg [2:0] cntrl_in_spk_reg_mask,             // read in_spk input layer
    output reg cntrl_in_spk_reg_we,                     // read in_spk input layer
    output reg cntrl_proc_reset,                        // reset in_spk (prob uselss)

    //u_b_processor


    //spk_memory_controler
    output reg [8:0] cntrl_spkblty_read_addr,           // spkblty read
    output reg [8:0] cntrl_spkblty_write_addr,          // spkblty write
    output reg cntrl_spkblty_write_we,                  // spkblty write
    output reg [2:0] cntrl_ac_spk_read_switch,          // spk read
    output reg [8:0] cntrl_ac_spk_read_addr,            // spk read
    output reg [8:0] cntrl_spk_write_addr,              // spk write
    output reg cntrl_spk_write_we,                      // spk write
    output reg [8:0] cntrl_in_spk_read_addr,            // in_spk read

    //u_b_memory_controler
    output reg [8:0] cntrl_potential_read_addr,         // potential read
    output reg [8:0] cntrl_potential_write_addr,        // potential write
    output reg cntrl_potential_write_we,                // potential write
    output reg [8:0] cntrl_beta_read_addr,              // beta read

    input wire clk, reset
    );

    reg [3:0] state;
    reg [7:0] time_step;
    reg [9:0] cnt_512;
    always @(posedge clk) begin
        case (state)
            `STATE_INIT: begin
                cntrl_proc_reset <= 1;
                cntrl_neu_reset <= 1;
                cnt_512 <= 0;
                time_step <= 0;
                state <= `STATE_INPUT_O;
                // in spk load
                cntrl_in_spk_reg_mask <= 0;
                cntrl_in_spk_reg_we <= 1;
                cntrl_in_spk_read_addr <= 0;
            end
            `STATE_INPUT_O: begin
                if (reset)
                    state <= `STATE_INIT;

                cnt_512 <= cnt_512 + 1;
                cntrl_proc_reset <= 0;
                cntrl_neu_reset <= 0;
                // 8 cycles
                if (cnt_512 < 7) begin
                    cntrl_in_spk_read_addr <= cntrl_in_spk_read_addr + 1;
                    cntrl_in_spk_reg_mask <= cntrl_in_spk_reg_mask + 1;
                end else begin
                    cntrl_in_spk_reg_we <= 0;
                    cntrl_ac_reset <= 1;
                    state <= `STATE_PRE_INPUT;
                end
            end
            `STATE_PRE_INPUT: begin
                cnt_512 <= 0;
                cntrl_ac_oen <= 0;

                // update addr
                // current layer:
                w_read_sram_addr  <= 0;
                // previous layer:
                cntrl_potential_read_addr <= 128;
                cntrl_beta_read_addr <= 128;
                cntrl_spkblty_read_addr <= 128;
                cntrl_potential_write_addr <= 128;
                cntrl_spkblty_write_addr <= 128;
                cntrl_spk_write_addr <= time_step + 128;

                // neuron select
                cntrl_u_out_select <= 0;
                cntrl_spk_select <= 0;
                cntrl_u_in_select <= 0;
                // write enable
                cntrl_spkblty_write_we <= 1;
                cntrl_spk_write_we <= 1;
                cntrl_potential_write_we <= 1;

                state <= `STATE_INPUT;
            end
            `STATE_INPUT: begin
                if (reset)
                    state <= `STATE_INIT;

                cntrl_ac_reset <= 0;
                cnt_512 <= cnt_512 + 1;
                // 64 cycles
                /* if (cnt_512 < 63) begin      // timing check */
                /*     cntrl_potential_read_addr <= cntrl_potential_read_addr + 1; */
                /*     cntrl_beta_read_addr <= cntrl_beta_read_addr + 1; */
                /*     cntrl_u_in_select <= cntrl_u_in_select + 1; */
                /*     cntrl_spk_write_addr <= cntrl_spk_write_addr + 1; */
                /*     cntrl_spkblty_read_addr <= cntrl_spkblty_read_addr + 1; */
                /*     cntrl_spkblty_write_addr <= cntrl_spkblty_write_addr + 1; */
                /* end */
                // 1 cycle
                if (cnt_512 < 1) begin
                    cntrl_ac_oen <= 1;
                    cntrl_ac_reset <= 1;
                end else begin
                    cntrl_ac_oen <= 0;
                    cntrl_spkblty_write_we <= 0;
                    cntrl_spk_write_we <= 0;
                    cntrl_potential_write_we <= 0;
                    state <= `STATE_P_H;
                end
                // finish
                /* if (cnt_512 == 64) begin       // timing check */
                /* end */
            end
            `STATE_P_H: begin
                cnt_512 <= 0;
                cntrl_ac_oen <= 0;
                // update addr
                // current layer:
                w_read_sram_addr  <= 1;
                // previous layer:
                cntrl_potential_read_addr <= 0;
                cntrl_beta_read_addr <= 0;
                cntrl_ac_spk_read_addr <= 0;
                cntrl_ac_spk_read_switch <= 0;
                cntrl_spkblty_read_addr <= 0;
                cntrl_potential_write_addr <= 0;
                cntrl_spkblty_write_addr <= 0;
                cntrl_spk_write_addr <= 0;
                // neuron select
                cntrl_u_out_select <= 0;
                cntrl_spk_select <= 0;
                cntrl_u_in_select <= 0;
                // write enable
                cntrl_spkblty_write_we <= 1;
                cntrl_spk_write_we <= 1;
                cntrl_potential_write_we <= 1;

                state <= `STATE_HIDDEN;
            end
            `STATE_HIDDEN: begin
                if (reset)
                    state <= `STATE_INIT;

                cntrl_ac_reset <= 0;
                cnt_512 <= cnt_512 + 1;
                // 512 cycles with 1 cycle delay
                // w read, spk read
                if (cnt_512 > 0) begin          // timing check
                    w_read_sram_addr <= w_read_sram_addr + 1;
                    cntrl_ac_spk_read_addr <= cntrl_ac_spk_read_addr + 1;
                    cntrl_ac_spk_read_switch <= cntrl_ac_spk_read_switch + 1;
                end
                // 64 cycles
                // potential r/w, spk w, spkblty r/w, beta r
                if (cnt_512 < 63) begin         // timing check
                    cntrl_potential_read_addr <= cntrl_potential_read_addr + 1;
                    cntrl_potential_write_addr <= cntrl_potential_write_addr + 1;
                    cntrl_spk_write_addr <= cntrl_spk_write_addr + 1;
                    cntrl_spkblty_read_addr <= cntrl_spkblty_read_addr + 1;
                    cntrl_spkblty_write_addr <= cntrl_spkblty_write_addr + 1;
                    cntrl_beta_read_addr <= cntrl_beta_read_addr + 1;
                    cntrl_u_out_select <= cntrl_u_out_select + 1;
                    cntrl_spk_select <= cntrl_spk_select + 1;
                    cntrl_u_in_select <= cntrl_u_in_select + 1;
                end else begin
                    cntrl_spkblty_write_we <= 0;
                    cntrl_spk_write_we <= 0;
                    cntrl_potential_write_we <= 0;
                end
                // finish
                if (cnt_512 == 255) begin       // timing check
                    cntrl_ac_oen <= 1;
                    cntrl_ac_reset <= 1;
                    state <= `STATE_PRE_OUTPUT;
                end
            end
            `STATE_PRE_OUTPUT: begin
                cnt_512 <= 0;
                cntrl_ac_oen <= 0;
                // update addr
                // current layer:
                w_read_sram_addr  <= 513;
                // previous layer:
                cntrl_potential_read_addr <= 64;
                cntrl_beta_read_addr <= 64;
                cntrl_ac_spk_read_addr <= 64;
                cntrl_ac_spk_read_switch <= 0;
                cntrl_spkblty_read_addr <= 64;
                cntrl_potential_write_addr <= 64;
                cntrl_spkblty_write_addr <= 64;
                cntrl_spk_write_addr <= 64;
                // neuron select
                cntrl_u_out_select <= 0;
                cntrl_spk_select <= 0;
                cntrl_u_in_select <= 0;
                // write enable
                cntrl_spkblty_write_we <= 1;
                cntrl_spk_write_we <= 1;
                cntrl_potential_write_we <= 1;
                // in spk load
                cntrl_in_spk_reg_mask <= 0;
                cntrl_in_spk_reg_we <= 1;
                cntrl_in_spk_read_addr <= (time_step << 3) + 8;

                state <= `STATE_OUTPUT;
            end
            `STATE_OUTPUT: begin
                if (reset)
                    state <= `STATE_INIT;

                cntrl_ac_reset <= 0;
                cnt_512 <= cnt_512 + 1;
                // 512 cycles with 1 cycle delay
                // w read, spk read
                if (cnt_512 > 0) begin          // timing check
                    w_read_sram_addr <= w_read_sram_addr + 1;
                    cntrl_ac_spk_read_addr <= cntrl_ac_spk_read_addr + 1;
                    cntrl_ac_spk_read_switch <= cntrl_ac_spk_read_switch + 1;
                end
                // 64 cycles
                // potential r/w, spk w, spkblty r/w, beta r
                if (cnt_512 < 63) begin         // timing check
                    cntrl_beta_read_addr <= cntrl_beta_read_addr + 1;
                    cntrl_potential_read_addr <= cntrl_potential_read_addr + 1;
                    cntrl_potential_write_addr <= cntrl_potential_write_addr + 1;
                    cntrl_spk_write_addr <= cntrl_spk_write_addr + 1;
                    cntrl_spkblty_read_addr <= cntrl_spkblty_read_addr + 1;
                    cntrl_spkblty_write_addr <= cntrl_spkblty_write_addr + 1;
                    cntrl_u_out_select <= cntrl_u_out_select + 1;
                    cntrl_spk_select <= cntrl_spk_select + 1;
                end else begin
                    cntrl_spkblty_write_we <= 0;
                    cntrl_spk_write_we <= 0;
                    cntrl_potential_write_we <= 0;
                end
                // 8 cycles
                if (cnt_512 < 7) begin
                    cntrl_in_spk_read_addr <= cntrl_in_spk_read_addr + 1;
                    cntrl_in_spk_reg_mask <= cntrl_in_spk_reg_mask + 1;
                end else begin
                    cntrl_in_spk_reg_we <= 0;
                end
                // finish
                if (cnt_512 == 255) begin       // timing check
                    if (time_step < 128) begin
                        cntrl_ac_oen <= 1;
                        cntrl_ac_reset <= 1;
                        time_step <= time_step + 1;
                        state <= `STATE_PRE_INPUT;
                    end else begin
                        state <= `STATE_INIT;
                    end
                end
            end
            default: state <= `STATE_INIT;
        endcase
    end

    `ifdef COCOTB_SIM
    initial begin
    $dumpfile ("control_unit_256.vcd");
    $dumpvars (0, control_unit_256);
    #1;
    end
    `endif

endmodule

verilog-workbench/control_unit_256.vcd
$date
	Mon Nov  7 12:45:20 2022
$end
$version
	Icarus Verilog
$end
$timescale
	1ps
$end
$scope module control_unit_256 $end
$var wire 1 ! clk $end
$var wire 1 " reset $end
$var reg 10 # cnt_512 [9:0] $end
$var reg 1 $ cntrl_ac_oen $end
$var reg 1 % cntrl_ac_reset $end
$var reg 9 & cntrl_ac_spk_read_addr [8:0] $end
$var reg 3 ' cntrl_ac_spk_read_switch [2:0] $end
$var reg 9 ( cntrl_beta_read_addr [8:0] $end
$var reg 9 ) cntrl_in_spk_read_addr [8:0] $end
$var reg 3 * cntrl_in_spk_reg_mask [2:0] $end
$var reg 1 + cntrl_in_spk_reg_we $end
$var reg 1 , cntrl_neu_reset $end
$var reg 9 - cntrl_potential_read_addr [8:0] $end
$var reg 9 . cntrl_potential_write_addr [8:0] $end
$var reg 1 / cntrl_potential_write_we $end
$var reg 1 0 cntrl_proc_reset $end
$var reg 1 1 cntrl_spk_select $end
$var reg 9 2 cntrl_spk_write_addr [8:0] $end
$var reg 1 3 cntrl_spk_write_we $end
$var reg 9 4 cntrl_spkblty_read_addr [8:0] $end
$var reg 9 5 cntrl_spkblty_write_addr [8:0] $end
$var reg 1 6 cntrl_spkblty_write_we $end
$var reg 6 7 cntrl_u_in_select [5:0] $end
$var reg 6 8 cntrl_u_out_select [5:0] $end
$var reg 4 9 state [3:0] $end
$var reg 8 : time_step [7:0] $end
$var reg 11 ; w_read_sram_addr [10:0] $end
$upscope $end
$enddefinitions $end
#0
$dumpvars
bx ;
bx :
b0 9
bx 8
bx 7
x6
bx 5
bx 4
x3
bx 2
x1
x0
x/
bx .
bx -
x,
x+
bx *
bx )
bx (
bx '
bx &
x%
x$
bx #
1"
1!
$end
#20000
0!
#40000
b0 )
1+
b0 *
b1 9
b0 :
b0 #
1,
10
1!
#60000
0!
#80000
b1 *
b1 )
0,
00
b1 #
b0 9
1!
#100000
0!
#120000
b0 )
b0 *
b1 9
b0 #
1,
10
1!
#140000
0!
#160000
0"
b1 *
b1 )
0,
00
b1 #
b0 9
1!
#180000
0!
#200000
b0 )
b0 *
b1 9
b0 #
1,
10
1!
#220000
0!
#240000
b1 *
b1 )
0,
00
b1 #
1!
#260000
0!
#280000
b10 *
b10 )
b10 #
1!
#300000
0!
#320000
b11 *
b11 )
b11 #
1!
#340000
0!
#360000
b100 *
b100 )
b100 #
1!
#380000
0!
#400000
b101 *
b101 )
b101 #
1!
#420000
0!
#440000
b110 *
b110 )
b110 #
1!
#460000
0!
#480000
b111 *
b111 )
b111 #
1!
#500000
0!
#520000
b10 9
1%
0+
b1000 #
1!
#540000
0!
#560000
b11 9
1/
13
16
b0 7
01
b0 8
b10000000 2
b10000000 5
b10000000 .
b10000000 4
b10000000 (
b10000000 -
b0 ;
0$
b0 #
1!
#580000
0!
#600000
1$
b1 #
1%
1!
#620000
0!
#640000
b100 9
0/
03
06
0$
b10 #
0%
1!
#660000
0!
#680000
b101 9
1/
13
16
b0 2
b0 5
b0 .
b0 4
b0 '
b0 &
b0 (
b0 -
b1 ;
b0 #
1!
#700000
0!
#720000
b1 7
11
b1 8
b1 (
b1 5
b1 4
b1 2
b1 .
b1 -
b1 #
1!
#740000
0!
#760000
b10 7
01
b10 8
b10 (
b10 5
b10 4
b10 2
b10 .
b10 -
b1 '
b1 &
b10 ;
b10 #
1!
#780000
0!
#800000
b11 7
11
b11 8
b11 (
b11 5
b11 4
b11 2
b11 .
b11 -
b10 '
b10 &
b11 ;
b11 #
1!
#820000
0!
#840000
b100 7
01
b100 8
b100 (
b100 5
b100 4
b100 2
b100 .
b100 -
b11 '
b11 &
b100 ;
b100 #
1!
#860000
0!
#880000
b101 7
11
b101 8
b101 (
b101 5
b101 4
b101 2
b101 .
b101 -
b100 '
b100 &
b101 ;
b101 #
1!
#900000
0!
#920000
b110 7
01
b110 8
b110 (
b110 5
b110 4
b110 2
b110 .
b110 -
b101 '
b101 &
b110 ;
b110 #
1!
#940000
0!
#960000
b111 7
11
b111 8
b111 (
b111 5
b111 4
b111 2
b111 .
b111 -
b110 '
b110 &
b111 ;
b111 #
1!
#980000
0!
#1000000
b1000 7
01
b1000 8
b1000 (
b1000 5
b1000 4
b1000 2
b1000 .
b1000 -
b111 '
b111 &
b1000 ;
b1000 #
1!
#1020000
0!
#1040000
b1001 7
11
b1001 8
b1001 (
b1001 5
b1001 4
b1001 2
b1001 .
b1001 -
b0 '
b1000 &
b1001 ;
b1001 #
1!
#1060000
0!
#1080000
b1010 7
01
b1010 8
b1010 (
b1010 5
b1010 4
b1010 2
b1010 .
b1010 -
b1 '
b1001 &
b1010 ;
b1010 #
1!
#1100000
0!
#1120000
b1011 7
11
b1011 8
b1011 (
b1011 5
b1011 4
b1011 2
b1011 .
b1011 -
b10 '
b1010 &
b1011 ;
b1011 #
1!
#1140000
0!
#1160000
b1100 7
01
b1100 8
b1100 (
b1100 5
b1100 4
b1100 2
b1100 .
b1100 -
b11 '
b1011 &
b1100 ;
b1100 #
1!
#1180000
0!
#1200000
b1101 7
11
b1101 8
b1101 (
b1101 5
b1101 4
b1101 2
b1101 .
b1101 -
b100 '
b1100 &
b1101 ;
b1101 #
1!
#1220000
0!
#1240000
b1110 7
01
b1110 8
b1110 (
b1110 5
b1110 4
b1110 2
b1110 .
b1110 -
b101 '
b1101 &
b1110 ;
b1110 #
1!
#1260000
0!
#1280000
b1111 7
11
b1111 8
b1111 (
b1111 5
b1111 4
b1111 2
b1111 .
b1111 -
b110 '
b1110 &
b1111 ;
b1111 #
1!
#1300000
0!
#1320000
b10000 7
01
b10000 8
b10000 (
b10000 5
b10000 4
b10000 2
b10000 .
b10000 -
b111 '
b1111 &
b10000 ;
b10000 #
1!
#1340000
0!
#1360000
b10001 7
11
b10001 8
b10001 (
b10001 5
b10001 4
b10001 2
b10001 .
b10001 -
b0 '
b10000 &
b10001 ;
b10001 #
1!
#1380000
0!
#1400000
b10010 7
01
b10010 8
b10010 (
b10010 5
b10010 4
b10010 2
b10010 .
b10010 -
b1 '
b10001 &
b10010 ;
b10010 #
1!
#1420000
0!
#1440000
b10011 7
11
b10011 8
b10011 (
b10011 5
b10011 4
b10011 2
b10011 .
b10011 -
b10 '
b10010 &
b10011 ;
b10011 #
1!
#1460000
0!
#1480000
b10100 7
01
b10100 8
b10100 (
b10100 5
b10100 4
b10100 2
b10100 .
b10100 -
b11 '
b10011 &
b10100 ;
b10100 #
1!
#1500000
0!
#1520000
b10101 7
11
b10101 8
b10101 (
b10101 5
b10101 4
b10101 2
b10101 .
b10101 -
b100 '
b10100 &
b10101 ;
b10101 #
1!
#1540000
0!
#1560000
b10110 7
01
b10110 8
b10110 (
b10110 5
b10110 4
b10110 2
b10110 .
b10110 -
b101 '
b10101 &
b10110 ;
b10110 #
1!
#1580000
0!
#1600000
b10111 7
11
b10111 8
b10111 (
b10111 5
b10111 4
b10111 2
b10111 .
b10111 -
b110 '
b10110 &
b10111 ;
b10111 #
1!
#1620000
0!
#1640000
b11000 7
01
b11000 8
b11000 (
b11000 5
b11000 4
b11000 2
b11000 .
b11000 -
b111 '
b10111 &
b11000 ;
b11000 #
1!
#1660000
0!
#1680000
b11001 7
11
b11001 8
b11001 (
b11001 5
b11001 4
b11001 2
b11001 .
b11001 -
b0 '
b11000 &
b11001 ;
b11001 #
1!
#1700000
0!
#1720000
b11010 7
01
b11010 8
b11010 (
b11010 5
b11010 4
b11010 2
b11010 .
b11010 -
b1 '
b11001 &
b11010 ;
b11010 #
1!
#1740000
0!
#1760000
b11011 7
11
b11011 8
b11011 (
b11011 5
b11011 4
b11011 2
b11011 .
b11011 -
b10 '
b11010 &
b11011 ;
b11011 #
1!
#1780000
0!
#1800000
b11100 7
01
b11100 8
b11100 (
b11100 5
b11100 4
b11100 2
b11100 .
b11100 -
b11 '
b11011 &
b11100 ;
b11100 #
1!
#1820000
0!
#1840000
b11101 7
11
b11101 8
b11101 (
b11101 5
b11101 4
b11101 2
b11101 .
b11101 -
b100 '
b11100 &
b11101 ;
b11101 #
1!
#1860000
0!
#1880000
b11110 7
01
b11110 8
b11110 (
b11110 5
b11110 4
b11110 2
b11110 .
b11110 -
b101 '
b11101 &
b11110 ;
b11110 #
1!
#1900000
0!
#1920000
b11111 7
11
b11111 8
b11111 (
b11111 5
b11111 4
b11111 2
b11111 .
b11111 -
b110 '
b11110 &
b11111 ;
b11111 #
1!
#1940000
0!
#1960000
b100000 7
01
b100000 8
b100000 (
b100000 5
b100000 4
b100000 2
b100000 .
b100000 -
b111 '
b11111 &
b100000 ;
b100000 #
1!
#1980000
0!
#2000000
b100001 7
11
b100001 8
b100001 (
b100001 5
b100001 4
b100001 2
b100001 .
b100001 -
b0 '
b100000 &
b100001 ;
b100001 #
1!
#2020000
0!
#2040000
b100010 7
01
b100010 8
b100010 (
b100010 5
b100010 4
b100010 2
b100010 .
b100010 -
b1 '
b100001 &
b100010 ;
b100010 #
1!
#2060000
0!
#2080000
b100011 7
11
b100011 8
b100011 (
b100011 5
b100011 4
b100011 2
b100011 .
b100011 -
b10 '
b100010 &
b100011 ;
b100011 #
1!
#2100000
0!
#2120000
b100100 7
01
b100100 8
b100100 (
b100100 5
b100100 4
b100100 2
b100100 .
b100100 -
b11 '
b100011 &
b100100 ;
b100100 #
1!
#2140000
0!
#2160000
b100101 7
11
b100101 8
b100101 (
b100101 5
b100101 4
b100101 2
b100101 .
b100101 -
b100 '
b100100 &
b100101 ;
b100101 #
1!
#2180000
0!
#2200000
b100110 7
01
b100110 8
b100110 (
b100110 5
b100110 4
b100110 2
b100110 .
b100110 -
b101 '
b100101 &
b100110 ;
b100110 #
1!
#2220000
0!
#2240000
b100111 7
11
b100111 8
b100111 (
b100111 5
b100111 4
b100111 2
b100111 .
b100111 -
b110 '
b100110 &
b100111 ;
b100111 #
1!
#2260000
0!
#2280000
b101000 7
01
b101000 8
b101000 (
b101000 5
b101000 4
b101000 2
b101000 .
b101000 -
b111 '
b100111 &
b101000 ;
b101000 #
1!
#2300000
0!
#2320000
b101001 7
11
b101001 8
b101001 (
b101001 5
b101001 4
b101001 2
b101001 .
b101001 -
b0 '
b101000 &
b101001 ;
b101001 #
1!
#2340000
0!
#2360000
b101010 7
01
b101010 8
b101010 (
b101010 5
b101010 4
b101010 2
b101010 .
b101010 -
b1 '
b101001 &
b101010 ;
b101010 #
1!
#2380000
0!
#2400000
b101011 7
11
b101011 8
b101011 (
b101011 5
b101011 4
b101011 2
b101011 .
b101011 -
b10 '
b101010 &
b101011 ;
b101011 #
1!
#2420000
0!
#2440000
b101100 7
01
b101100 8
b101100 (
b101100 5
b101100 4
b101100 2
b101100 .
b101100 -
b11 '
b101011 &
b101100 ;
b101100 #
1!
#2460000
0!
#2480000
b101101 7
11
b101101 8
b101101 (
b101101 5
b101101 4
b101101 2
b101101 .
b101101 -
b100 '
b101100 &
b101101 ;
b101101 #
1!
#2500000
0!
#2520000
b101110 7
01
b101110 8
b101110 (
b101110 5
b101110 4
b101110 2
b101110 .
b101110 -
b101 '
b101101 &
b101110 ;
b101110 #
1!
#2540000
0!
#2560000
b101111 7
11
b101111 8
b101111 (
b101111 5
b101111 4
b101111 2
b101111 .
b101111 -
b110 '
b101110 &
b101111 ;
b101111 #
1!
#2580000
0!
#2600000
b110000 7
01
b110000 8
b110000 (
b110000 5
b110000 4
b110000 2
b110000 .
b110000 -
b111 '
b101111 &
b110000 ;
b110000 #
1!
#2620000
0!
#2640000
b110001 7
11
b110001 8
b110001 (
b110001 5
b110001 4
b110001 2
b110001 .
b110001 -
b0 '
b110000 &
b110001 ;
b110001 #
1!
#2660000
0!
#2680000
b110010 7
01
b110010 8
b110010 (
b110010 5
b110010 4
b110010 2
b110010 .
b110010 -
b1 '
b110001 &
b110010 ;
b110010 #
1!
#2700000
0!
#2720000
b110011 7
11
b110011 8
b110011 (
b110011 5
b110011 4
b110011 2
b110011 .
b110011 -
b10 '
b110010 &
b110011 ;
b110011 #
1!
#2740000
0!
#2760000
b110100 7
01
b110100 8
b110100 (
b110100 5
b110100 4
b110100 2
b110100 .
b110100 -
b11 '
b110011 &
b110100 ;
b110100 #
1!
#2780000
0!
#2800000
b110101 7
11
b110101 8
b110101 (
b110101 5
b110101 4
b110101 2
b110101 .
b110101 -
b100 '
b110100 &
b110101 ;
b110101 #
1!
#2820000
0!
#2840000
b110110 7
01
b110110 8
b110110 (
b110110 5
b110110 4
b110110 2
b110110 .
b110110 -
b101 '
b110101 &
b110110 ;
b110110 #
1!
#2860000
0!
#2880000
b110111 7
11
b110111 8
b110111 (
b110111 5
b110111 4
b110111 2
b110111 .
b110111 -
b110 '
b110110 &
b110111 ;
b110111 #
1!
#2900000
0!
#2920000
b111000 7
01
b111000 8
b111000 (
b111000 5
b111000 4
b111000 2
b111000 .
b111000 -
b111 '
b110111 &
b111000 ;
b111000 #
1!
#2940000
0!
#2960000
b111001 7
11
b111001 8
b111001 (
b111001 5
b111001 4
b111001 2
b111001 .
b111001 -
b0 '
b111000 &
b111001 ;
b111001 #
1!
#2980000
0!
#3000000
b111010 7
01
b111010 8
b111010 (
b111010 5
b111010 4
b111010 2
b111010 .
b111010 -
b1 '
b111001 &
b111010 ;
b111010 #
1!
#3020000
0!
#3040000
b111011 7
11
b111011 8
b111011 (
b111011 5
b111011 4
b111011 2
b111011 .
b111011 -
b10 '
b111010 &
b111011 ;
b111011 #
1!
#3060000
0!
#3080000
b111100 7
01
b111100 8
b111100 (
b111100 5
b111100 4
b111100 2
b111100 .
b111100 -
b11 '
b111011 &
b111100 ;
b111100 #
1!
#3100000
0!
#3120000
b111101 7
11
b111101 8
b111101 (
b111101 5
b111101 4
b111101 2
b111101 .
b111101 -
b100 '
b111100 &
b111101 ;
b111101 #
1!
#3140000
0!
#3160000
b111110 7
01
b111110 8
b111110 (
b111110 5
b111110 4
b111110 2
b111110 .
b111110 -
b101 '
b111101 &
b111110 ;
b111110 #
1!
#3180000
0!
#3200000
b111111 7
11
b111111 8
b111111 (
b111111 5
b111111 4
b111111 2
b111111 .
b111111 -
b110 '
b111110 &
b111111 ;
b111111 #
1!
#3220000
0!
#3240000
0/
03
06
b111 '
b111111 &
b1000000 ;
b1000000 #
1!
#3260000
0!
#3280000
b0 '
b1000000 &
b1000001 ;
b1000001 #
1!
#3300000
0!
#3320000
b1 '
b1000001 &
b1000010 ;
b1000010 #
1!
#3340000
0!
#3360000
b10 '
b1000010 &
b1000011 ;
b1000011 #
1!
#3380000
0!
#3400000
b11 '
b1000011 &
b1000100 ;
b1000100 #
1!
#3420000
0!
#3440000
b100 '
b1000100 &
b1000101 ;
b1000101 #
1!
#3460000
0!
#3480000
b101 '
b1000101 &
b1000110 ;
b1000110 #
1!
#3500000
0!
#3520000
b110 '
b1000110 &
b1000111 ;
b1000111 #
1!
#3540000
0!
#3560000
b111 '
b1000111 &
b1001000 ;
b1001000 #
1!
#3580000
0!
#3600000
b0 '
b1001000 &
b1001001 ;
b1001001 #
1!
#3620000
0!
#3640000
b1 '
b1001001 &
b1001010 ;
b1001010 #
1!
#3660000
0!
#3680000
b10 '
b1001010 &
b1001011 ;
b1001011 #
1!
#3700000
0!
#3720000
b11 '
b1001011 &
b1001100 ;
b1001100 #
1!
#3740000
0!
#3760000
b100 '
b1001100 &
b1001101 ;
b1001101 #
1!
#3780000
0!
#3800000
b101 '
b1001101 &
b1001110 ;
b1001110 #
1!
#3820000
0!
#3840000
b110 '
b1001110 &
b1001111 ;
b1001111 #
1!
#3860000
0!
#3880000
b111 '
b1001111 &
b1010000 ;
b1010000 #
1!
#3900000
0!
#3920000
b0 '
b1010000 &
b1010001 ;
b1010001 #
1!
#3940000
0!
#3960000
b1 '
b1010001 &
b1010010 ;
b1010010 #
1!
#3980000
0!
#4000000
b10 '
b1010010 &
b1010011 ;
b1010011 #
1!
#4020000
0!
#4040000
b11 '
b1010011 &
b1010100 ;
b1010100 #
1!
#4060000
0!
#4080000
b100 '
b1010100 &
b1010101 ;
b1010101 #
1!
#4100000
0!
#4120000
b101 '
b1010101 &
b1010110 ;
b1010110 #
1!
#4140000
0!
#4160000
b110 '
b1010110 &
b1010111 ;
b1010111 #
1!
#4180000
0!
#4200000
b111 '
b1010111 &
b1011000 ;
b1011000 #
1!
#4220000
0!
#4240000
b0 '
b1011000 &
b1011001 ;
b1011001 #
1!
#4260000
0!
#4280000
b1 '
b1011001 &
b1011010 ;
b1011010 #
1!
#4300000
0!
#4320000
b10 '
b1011010 &
b1011011 ;
b1011011 #
1!
#4340000
0!
#4360000
b11 '
b1011011 &
b1011100 ;
b1011100 #
1!
#4380000
0!
#4400000
b100 '
b1011100 &
b1011101 ;
b1011101 #
1!
#4420000
0!
#4440000
b101 '
b1011101 &
b1011110 ;
b1011110 #
1!
#4460000
0!
#4480000
b110 '
b1011110 &
b1011111 ;
b1011111 #
1!
#4500000
0!
#4520000
b111 '
b1011111 &
b1100000 ;
b1100000 #
1!
#4540000
0!
#4560000
b0 '
b1100000 &
b1100001 ;
b1100001 #
1!
#4580000
0!
#4600000
b1 '
b1100001 &
b1100010 ;
b1100010 #
1!
#4620000
0!
#4640000
b10 '
b1100010 &
b1100011 ;
b1100011 #
1!
#4660000
0!
#4680000
b11 '
b1100011 &
b1100100 ;
b1100100 #
1!
#4700000
0!
#4720000
b100 '
b1100100 &
b1100101 ;
b1100101 #
1!
#4740000
0!
#4760000
b101 '
b1100101 &
b1100110 ;
b1100110 #
1!
#4780000
0!
#4800000
b110 '
b1100110 &
b1100111 ;
b1100111 #
1!
#4820000
0!
#4840000
b111 '
b1100111 &
b1101000 ;
b1101000 #
1!
#4860000
0!
#4880000
b0 '
b1101000 &
b1101001 ;
b1101001 #
1!
#4900000
0!
#4920000
b1 '
b1101001 &
b1101010 ;
b1101010 #
1!
#4940000
0!
#4960000
b10 '
b1101010 &
b1101011 ;
b1101011 #
1!
#4980000
0!
#5000000
b11 '
b1101011 &
b1101100 ;
b1101100 #
1!
#5020000
0!
#5040000
b100 '
b1101100 &
b1101101 ;
b1101101 #
1!
#5060000
0!
#5080000
b101 '
b1101101 &
b1101110 ;
b1101110 #
1!
#5100000
0!
#5120000
b110 '
b1101110 &
b1101111 ;
b1101111 #
1!
#5140000
0!
#5160000
b111 '
b1101111 &
b1110000 ;
b1110000 #
1!
#5180000
0!
#5200000
b0 '
b1110000 &
b1110001 ;
b1110001 #
1!
#5220000
0!
#5240000
b1 '
b1110001 &
b1110010 ;
b1110010 #
1!
#5260000
0!
#5280000
b10 '
b1110010 &
b1110011 ;
b1110011 #
1!
#5300000
0!
#5320000
b11 '
b1110011 &
b1110100 ;
b1110100 #
1!
#5340000
0!
#5360000
b100 '
b1110100 &
b1110101 ;
b1110101 #
1!
#5380000
0!
#5400000
b101 '
b1110101 &
b1110110 ;
b1110110 #
1!
#5420000
0!
#5440000
b110 '
b1110110 &
b1110111 ;
b1110111 #
1!
#5460000
0!
#5480000
b111 '
b1110111 &
b1111000 ;
b1111000 #
1!
#5500000
0!
#5520000
b0 '
b1111000 &
b1111001 ;
b1111001 #
1!
#5540000
0!
#5560000
b1 '
b1111001 &
b1111010 ;
b1111010 #
1!
#5580000
0!
#5600000
b10 '
b1111010 &
b1111011 ;
b1111011 #
1!
#5620000
0!
#5640000
b11 '
b1111011 &
b1111100 ;
b1111100 #
1!
#5660000
0!
#5680000
b100 '
b1111100 &
b1111101 ;
b1111101 #
1!
#5700000
0!
#5720000
b101 '
b1111101 &
b1111110 ;
b1111110 #
1!
#5740000
0!
#5760000
b110 '
b1111110 &
b1111111 ;
b1111111 #
1!
#5780000
0!
#5800000
b111 '
b1111111 &
b10000000 ;
b10000000 #
1!
#5820000
0!
#5840000
b0 '
b10000000 &
b10000001 ;
b10000001 #
1!
#5860000
0!
#5880000
b1 '
b10000001 &
b10000010 ;
b10000010 #
1!
#5900000
0!
#5920000
b10 '
b10000010 &
b10000011 ;
b10000011 #
1!
#5940000
0!
#5960000
b11 '
b10000011 &
b10000100 ;
b10000100 #
1!
#5980000
0!
#6000000
b100 '
b10000100 &
b10000101 ;
b10000101 #
1!
#6020000
0!
