verilog-workbench/src_new/shift_add_mult.v
`default_nettype none
`timescale 1ns/1ns

module shift_add_mult (
    input wire [3:0] beta,
    input wire [7:0] potential,
    output reg [7:0] mult_ans
    );

    always @(*) begin
        case (beta)
            4'd0:   mult_ans <= 0;
            4'd1:   mult_ans <= potential >> 3;
            4'd2:   mult_ans <= potential >> 2;
            4'd3:   mult_ans <= (potential >> 2) + (potential >> 3);
            4'd4:   mult_ans <= (potential >> 1); 
            4'd5:   mult_ans <= (potential >> 1) + (potential >> 3);
            4'd6:   mult_ans <= (potential >> 1) + (potential >> 2);
            4'd7:   mult_ans <= (potential >> 1) + (potential >> 2) + (potential >> 3);
            4'd8:   mult_ans <= potential;
            default:    mult_ans <= 4'bx;
        endcase
    end

    `ifdef COCOTB_SIM 
    initial begin
    $dumpfile ("shift_add_mult.vcd");
    $dumpvars (0, shift_add_mult);
    #1;
    end
    `endif

endmodule

verilog-workbench/shift_add_mult.vcd
$date
	Wed Sep 21 14:04:05 2022
$end
$version
	Icarus Verilog
$end
$timescale
	1ps
$end
$scope module shift_add_mult $end
$var wire 4 ! beta [3:0] $end
$var wire 8 " potential [7:0] $end
$var reg 8 # mult_ans [7:0] $end
$upscope $end
$enddefinitions $end
#0
$dumpvars
b0 #
b0 "
b0 !
$end
#10000000
b1 "
#20000000
b10 "
#30000000
b11 "
#40000000
b100 "
#50000000
b101 "
#60000000
b110 "
#70000000
b111 "
#80000000
b1000 "
#90000000
b1001 "
#100000000
b1010 "
#110000000
b1011 "
#120000000
b1100 "
#130000000
b1101 "
#140000000
b1110 "
#150000000
b1111 "
#160000000
b10000 "
#170000000
b10001 "
#180000000
b10010 "
#190000000
b10011 "
#200000000
b10100 "
#210000000
b10101 "
#220000000
b10110 "
#230000000
b10111 "
#240000000
b11000 "
#250000000
b11001 "
#260000000
b11010 "
#270000000
b11011 "
#280000000
b11100 "
#290000000
b11101 "
#300000000
b11110 "
#310000000
b11111 "
#320000000
b100000 "
#330000000
b100001 "
#340000000
b100010 "
#350000000
b100011 "
#360000000
b100100 "
#370000000
b100101 "
#380000000
b100110 "
#390000000
b100111 "
#400000000
b101000 "
#410000000
b101001 "
#420000000
b101010 "
#430000000
b101011 "
#440000000
b101100 "
#450000000
b101101 "
#460000000
b101110 "
#470000000
b101111 "
#480000000
b110000 "
#490000000
b110001 "
#500000000
b110010 "
#510000000
b110011 "
#520000000
b110100 "
#530000000
b110101 "
#540000000
b110110 "
#550000000
b110111 "
#560000000
b111000 "
#570000000
b111001 "
#580000000
b111010 "
#590000000
b111011 "
#600000000
b111100 "
#610000000
b111101 "
#620000000
b111110 "
#630000000
b111111 "
#640000000
b1000000 "
#650000000
b1000001 "
#660000000
b1000010 "
#670000000
b1000011 "
#680000000
b1000100 "
#690000000
b1000101 "
#700000000
b1000110 "
#710000000
b1000111 "
#720000000
b1001000 "
#730000000
b1001001 "
#740000000
b1001010 "
#750000000
b1001011 "
#760000000
b1001100 "
#770000000
b1001101 "
#780000000
b1001110 "
#790000000
b1001111 "
#800000000
b1010000 "
#810000000
b1010001 "
#820000000
b1010010 "
#830000000
b1010011 "
#840000000
b1010100 "
#850000000
b1010101 "
#860000000
b1010110 "
#870000000
b1010111 "
#880000000
b1011000 "
#890000000
b1011001 "
#900000000
b1011010 "
#910000000
b1011011 "
#920000000
b1011100 "
#930000000
b1011101 "
#940000000
b1011110 "
#950000000
b1011111 "
#960000000
b1100000 "
#970000000
b1100001 "
#980000000
b1100010 "
#990000000
b1100011 "
#1000000000
b1100100 "
#1010000000
b1100101 "
#1020000000
b1100110 "
#1030000000
b1100111 "
#1040000000
b1101000 "
#1050000000
b1101001 "
#1060000000
b1101010 "
#1070000000
b1101011 "
#1080000000
b1101100 "
#1090000000
b1101101 "
#1100000000
b1101110 "
#1110000000
b1101111 "
#1120000000
b1110000 "
#1130000000
b1110001 "
#1140000000
b1110010 "
#1150000000
b1110011 "
#1160000000
b1110100 "
#1170000000
b1110101 "
#1180000000
b1110110 "
#1190000000
b1110111 "
#1200000000
b1111000 "
#1210000000
b1111001 "
#1220000000
b1111010 "
#1230000000
b1111011 "
#1240000000
b1111100 "
#1250000000
b1111101 "
#1260000000
b1111110 "
#1270000000
b1111111 "
#1280000000
b10000000 "
#1290000000
b10000001 "
#1300000000
b10000010 "
#1310000000
b10000011 "
#1320000000
b10000100 "
#1330000000
b10000101 "
#1340000000
b10000110 "
#1350000000
b10000111 "
#1360000000
b10001000 "
#1370000000
b10001001 "
#1380000000
b10001010 "
#1390000000
b10001011 "
#1400000000
b10001100 "
#1410000000
b10001101 "
#1420000000
b10001110 "
#1430000000
b10001111 "
#1440000000
b10010000 "
#1450000000
b10010001 "
#1460000000
b10010010 "
#1470000000
b10010011 "
#1480000000
b10010100 "
#1490000000
b10010101 "
#1500000000
b10010110 "
#1510000000
b10010111 "
#1520000000
b10011000 "
#1530000000
b10011001 "
#1540000000
b10011010 "
#1550000000
b10011011 "
#1560000000
b10011100 "
#1570000000
b10011101 "
#1580000000
b10011110 "
#1590000000
b10011111 "
#1600000000
b10100000 "
#1610000000
b10100001 "
#1620000000
b10100010 "
#1630000000
b10100011 "
#1640000000
b10100100 "
#1650000000
b10100101 "
#1660000000
b10100110 "
#1670000000
b10100111 "
#1680000000
b10101000 "
#1690000000
b10101001 "
#1700000000
b10101010 "
#1710000000
b10101011 "
#1720000000
b10101100 "
#1730000000
b10101101 "
#1740000000
b10101110 "
#1750000000
b10101111 "
#1760000000
b10110000 "
#1770000000
b10110001 "
#1780000000
b10110010 "
#1790000000
b10110011 "
#1800000000
b10110100 "
#1810000000
b10110101 "
#1820000000
b10110110 "
#1830000000
b10110111 "
#1840000000
b10111000 "
#1850000000
b10111001 "
#1860000000
b10111010 "
#1870000000
b10111011 "
#1880000000
b10111100 "
#1890000000
b10111101 "
#1900000000
b10111110 "
#1910000000
b10111111 "
#1920000000
b11000000 "
#1930000000
b11000001 "
#1940000000
b11000010 "
#1950000000
b11000011 "
#1960000000
b11000100 "
#1970000000
b11000101 "
#1980000000
b11000110 "
#1990000000
b11000111 "
#2000000000
b11001000 "
#2010000000
b11001001 "
#2020000000
b11001010 "
#2030000000
b11001011 "
#2040000000
b11001100 "
#2050000000
b11001101 "
#2060000000
b11001110 "
#2070000000
b11001111 "
#2080000000
b11010000 "
#2090000000
b11010001 "
#2100000000
b11010010 "
#2110000000
b11010011 "
#2120000000
b11010100 "
#2130000000
b11010101 "
#2140000000
b11010110 "
#2150000000
b11010111 "
#2160000000
b11011000 "
#2170000000
b11011001 "
#2180000000
b11011010 "
#2190000000
b11011011 "
#2200000000
b11011100 "
#2210000000
b11011101 "
#2220000000
b11011110 "
#2230000000
b11011111 "
#2240000000
b11100000 "
#2250000000
b11100001 "
#2260000000
b11100010 "
#2270000000
b11100011 "
#2280000000
b11100100 "
#2290000000
b11100101 "
#2300000000
b11100110 "
#2310000000
b11100111 "
#2320000000
b11101000 "
#2330000000
b11101001 "
#2340000000
b11101010 "
#2350000000
b11101011 "
#2360000000
b11101100 "
#2370000000
b11101101 "
#2380000000
b11101110 "
#2390000000
b11101111 "
#2400000000
b11110000 "
#2410000000
b11110001 "
#2420000000
b11110010 "
#2430000000
b11110011 "
#2440000000
b11110100 "
#2450000000
b11110101 "
#2460000000
b11110110 "
#2470000000
b11110111 "
#2480000000
b11111000 "
#2490000000
b11111001 "
#2500000000
b11111010 "
#2510000000
b11111011 "
#2520000000
b11111100 "
#2530000000
b11111101 "
#2540000000
b11111110 "
#2550000000
b11111111 "
#2560000000
b1 !
b0 "
#2570000000
b1 "
#2580000000
b10 "
#2590000000
b11 "
#2600000000
b100 "
#2610000000
b101 "
#2620000000
b110 "
#2630000000
b111 "
#2640000000
b1 #
b1000 "
#2650000000
b1001 "
#2660000000
b1010 "
#2670000000
b1011 "
#2680000000
b1100 "
#2690000000
b1101 "
#2700000000
b1110 "
#2710000000
b1111 "
#2720000000
b10 #
b10000 "
#2730000000
b10001 "
#2740000000
b10010 "
#2750000000
b10011 "
#2760000000
b10100 "
#2770000000
b10101 "
#2780000000
b10110 "
#2790000000
b10111 "
#2800000000
b11 #
b11000 "
#2810000000
b11001 "
#2820000000
b11010 "
#2830000000
b11011 "
#2840000000
b11100 "
#2850000000
b11101 "
#2860000000
b11110 "
#2870000000
b11111 "
#2880000000
b100 #
b100000 "
#2890000000
b100001 "
#2900000000
b100010 "
#2910000000
b100011 "
#2920000000
b100100 "
#2930000000
b100101 "
#2940000000
b100110 "
#2950000000
b100111 "
#2960000000
b101 #
b101000 "
#2970000000
b101001 "
#2980000000
b101010 "
#2990000000
b101011 "
#3000000000
b101100 "
#3010000000
b101101 "
#3020000000
b101110 "
#3030000000
b101111 "
#3040000000
b110 #
b110000 "
#3050000000
b110001 "
#3060000000
b110010 "
#3070000000
b110011 "
#3080000000
b110100 "
#3090000000
b110101 "
#3100000000
b110110 "
#3110000000
b110111 "
#3120000000
b111 #
b111000 "
#3130000000
b111001 "
#3140000000
b111010 "
#3150000000
b111011 "
#3160000000
b111100 "
#3170000000
b111101 "
#3180000000
b111110 "
#3190000000
b111111 "
#3200000000
b1000 #
b1000000 "
#3210000000
b1000001 "
#3220000000
b1000010 "
#3230000000
b1000011 "
#3240000000
b1000100 "
#3250000000
b1000101 "
#3260000000
b1000110 "
#3270000000
b1000111 "
#3280000000
b1001 #
b1001000 "
#3290000000
b1001001 "
#3300000000
b1001010 "
#3310000000
b1001011 "
#3320000000
b1001100 "
#3330000000
b1001101 "
#3340000000
b1001110 "
#3350000000
b1001111 "
#3360000000
b1010 #
b1010000 "
#3370000000
b1010001 "
#3380000000
b1010010 "
#3390000000
b1010011 "
#3400000000
b1010100 "
#3410000000
b1010101 "
#3420000000
b1010110 "
#3430000000
b1010111 "
#3440000000
b1011 #
b1011000 "
#3450000000
b1011001 "
#3460000000
b1011010 "
#3470000000
b1011011 "
#3480000000
b1011100 "
#3490000000
b1011101 "
#3500000000
b1011110 "
#3510000000
b1011111 "
#3520000000
b1100 #
b1100000 "
#3530000000
b1100001 "
#3540000000
b1100010 "
#3550000000
b1100011 "
#3560000000
b1100100 "
#3570000000
b1100101 "
#3580000000
b1100110 "
#3590000000
b1100111 "
#3600000000
b1101 #
b1101000 "
#3610000000
b1101001 "
#3620000000
b1101010 "
#3630000000
b1101011 "
#3640000000
b1101100 "
#3650000000
b1101101 "
#3660000000
b1101110 "
#3670000000
b1101111 "
#3680000000
b1110 #
b1110000 "
#3690000000
b1110001 "
#3700000000
b1110010 "
#3710000000
b1110011 "
#3720000000
b1110100 "
#3730000000
b1110101 "
#3740000000
b1110110 "
#3750000000
b1110111 "
#3760000000
b1111 #
b1111000 "
#3770000000
b1111001 "
#3780000000
b1111010 "
#3790000000
b1111011 "
#3800000000
b1111100 "
#3810000000
b1111101 "
#3820000000
b1111110 "
#3830000000
b1111111 "
#3840000000
b10000 #
b10000000 "
#3850000000
b10000001 "
#3860000000
b10000010 "
#3870000000
b10000011 "
#3880000000
b10000100 "
#3890000000
b10000101 "
#3900000000
b10000110 "
#3910000000
b10000111 "
#3920000000
b10001 #
b10001000 "
#3930000000
b10001001 "
#3940000000
b10001010 "
#3950000000
b10001011 "
#3960000000
b10001100 "
#3970000000
b10001101 "
#3980000000
b10001110 "
#3990000000
b10001111 "
#4000000000
b10010 #
b10010000 "
#4010000000
b10010001 "
#4020000000
b10010010 "
#4030000000
b10010011 "
#4040000000
b10010100 "
#4050000000
b10010101 "
#4060000000
b10010110 "
#4070000000
b10010111 "
#4080000000
b10011 #
b10011000 "
#4090000000
b10011001 "
#4100000000
b10011010 "
#4110000000
b10011011 "
#4120000000
b10011100 "
#4130000000
b10011101 "
#4140000000
b10011110 "
#4150000000
b10011111 "
#4160000000
b10100 #
b10100000 "
#4170000000
b10100001 "
#4180000000
b10100010 "
#4190000000
b10100011 "
#4200000000
b10100100 "
#4210000000
b10100101 "
#4220000000
b10100110 "
#4230000000
b10100111 "
#4240000000
b10101 #
b10101000 "
#4250000000
b10101001 "
#4260000000
b10101010 "
#4270000000
b10101011 "
#4280000000
b10101100 "
#4290000000
b10101101 "
#4300000000
b10101110 "
#4310000000
b10101111 "
#4320000000
b10110 #
b10110000 "
#4330000000
b10110001 "
#4340000000
b10110010 "
#4350000000
b10110011 "
#4360000000
b10110100 "
#4370000000
b10110101 "
#4380000000
b10110110 "
#4390000000
b10110111 "
#4400000000
b10111 #
b10111000 "
#4410000000
b10111001 "
#4420000000
b10111010 "
#4430000000
b10111011 "
#4440000000
b10111100 "
#4450000000
b10111101 "
#4460000000
b10111110 "
#4470000000
b10111111 "
#4480000000
b11000 #
b11000000 "
#4490000000
b11000001 "
#4500000000
b11000010 "
#4510000000
b11000011 "
#4520000000
b11000100 "
#4530000000
b11000101 "
#4540000000
b11000110 "
#4550000000
b11000111 "
#4560000000
b11001 #
b11001000 "
#4570000000
b11001001 "
#4580000000
b11001010 "
#4590000000
b11001011 "
#4600000000
b11001100 "
#4610000000
b11001101 "
#4620000000
b11001110 "
#4630000000
b11001111 "
#4640000000
b11010 #
b11010000 "
#4650000000
b11010001 "
#4660000000
b11010010 "
#4670000000
b11010011 "
#4680000000
b11010100 "
#4690000000
b11010101 "
#4700000000
b11010110 "
#4710000000
b11010111 "
#4720000000
b11011 #
b11011000 "
#4730000000
b11011001 "
#4740000000
b11011010 "
#4750000000
b11011011 "
#4760000000
b11011100 "
#4770000000
b11011101 "
#4780000000
b11011110 "
#4790000000
b11011111 "
#4800000000
b11100 #
b11100000 "
#4810000000
b11100001 "
#4820000000
b11100010 "
#4830000000
b11100011 "
#4840000000
b11100100 "
#4850000000
b11100101 "
#4860000000
b11100110 "
#4870000000
b11100111 "
#4880000000
b11101 #
b11101000 "
#4890000000
b11101001 "
#4900000000
b11101010 "
#4910000000
b11101011 "
#4920000000
b11101100 "
#4930000000
b11101101 "
#4940000000
b11101110 "
#4950000000
b11101111 "
#4960000000
b11110 #
b11110000 "
#4970000000
b11110001 "
#4980000000
b11110010 "
#4990000000
b11110011 "
#5000000000
b11110100 "
#5010000000
b11110101 "
#5020000000
b11110110 "
#5030000000
b11110111 "
#5040000000
b11111 #
b11111000 "
#5050000000
b11111001 "
#5060000000
b11111010 "
#5070000000
b11111011 "
#5080000000
b11111100 "
#5090000000
b11111101 "
#5100000000
b11111110 "
#5110000000
b11111111 "
#5120000000
b0 #
b10 !
b0 "
#5130000000
b1 "
#5140000000
b10 "
#5150000000
b11 "
#5160000000
b1 #
b100 "
#5170000000
b101 "
#5180000000
b110 "
#5190000000
b111 "
#5200000000
b10 #
b1000 "
#5210000000
b1001 "
#5220000000
b1010 "
#5230000000
b1011 "
#5240000000
b11 #
b1100 "
#5250000000
b1101 "
#5260000000
b1110 "
#5270000000
b1111 "
#5280000000
b100 #
b10000 "
#5290000000
b10001 "
#5300000000
b10010 "
#5310000000
b10011 "
#5320000000
b101 #
b10100 "
#5330000000
b10101 "
#5340000000
b10110 "
#5350000000
b10111 "
#5360000000
b110 #
b11000 "
#5370000000
b11001 "
#5380000000
b11010 "
#5390000000
b11011 "
#5400000000
b111 #
b11100 "
#5410000000
b11101 "
#5420000000
b11110 "
#5430000000
b11111 "
#5440000000
b1000 #
b100000 "
#5450000000
b100001 "
#5460000000
b100010 "
#5470000000
b100011 "
#5480000000
b1001 #
b100100 "
#5490000000
b100101 "
#5500000000
b100110 "
#5510000000
b100111 "
#5520000000
b1010 #
b101000 "
#5530000000
b101001 "
#5540000000
b101010 "
#5550000000
b101011 "
#5560000000
b1011 #
b101100 "
#5570000000
b101101 "
#5580000000
b101110 "
#5590000000
b101111 "
#5600000000
b1100 #
b110000 "
#5610000000
b110001 "
#5620000000
b110010 "
#5630000000
b110011 "
#5640000000
b1101 #
b110100 "
#5650000000
b110101 "
#5660000000
b110110 "
#5670000000
b110111 "
#5680000000
b1110 #
b111000 "
#5690000000
b111001 "
#5700000000
b111010 "
#5710000000
b111011 "
#5720000000
b1111 #
b111100 "
#5730000000
b111101 "
#5740000000
b111110 "
#5750000000
b111111 "
#5760000000
b10000 #
b1000000 "
#5770000000
b1000001 "
#5780000000
b1000010 "
#5790000000
b1000011 "
#5800000000
b10001 #
b1000100 "
#5810000000
b1000101 "
#5820000000
b1000110 "
#5830000000
b1000111 "
#5840000000
b10010 #
b1001000 "
#5850000000
b1001001 "
#5860000000
b1001010 "
#5870000000
b1001011 "
#5880000000
b10011 #
b1001100 "
#5890000000
b1001101 "
#5900000000
b1001110 "
#5910000000
b1001111 "
#5920000000
b10100 #
b1010000 "
#5930000000
b1010001 "
#5940000000
b1010010 "
#5950000000
b1010011 "
#5960000000
b10101 #
b1010100 "
#5970000000
b1010101 "
#5980000000
b1010110 "
#5990000000
b1010111 "
#6000000000
b10110 #
b1011000 "
#6010000000
b1011001 "
#6020000000
b1011010 "
#6030000000
b1011011 "
#6040000000
b10111 #
b1011100 "
#6050000000
b1011101 "
#6060000000
b1011110 "
#6070000000
b1011111 "
#6080000000
b11000 #
b1100000 "
#6090000000
b1100001 "
#6100000000
b1100010 "
#6110000000
b1100011 "
#6120000000
b11001 #
b1100100 "
#6130000000
b1100101 "
#6140000000
b1100110 "
#6150000000
b1100111 "
#6160000000
b11010 #
b1101000 "
#6170000000
b1101001 "
#6180000000
b1101010 "
#6190000000
b1101011 "
#6200000000
b11011 #
b1101100 "
#6210000000
b1101101 "
#6220000000
b1101110 "
#6230000000
b1101111 "
#6240000000
b11100 #
b1110000 "
#6250000000
b1110001 "
#6260000000
b1110010 "
#6270000000
b1110011 "
#6280000000
b11101 #
b1110100 "
#6290000000
b1110101 "
#6300000000
b1110110 "
#6310000000
b1110111 "
#6320000000
b11110 #
b1111000 "
#6330000000
b1111001 "
#6340000000
b1111010 "
#6350000000
b1111011 "
#6360000000
b11111 #
b1111100 "
#6370000000
b1111101 "
#6380000000
b1111110 "
#6390000000
b1111111 "
#6400000000
b100000 #
b10000000 "
#6410000000
b10000001 "
#6420000000
b10000010 "
#6430000000
b10000011 "
#6440000000
b100001 #
b10000100 "
#6450000000
b10000101 "
#6460000000
b10000110 "
#6470000000
b10000111 "
#6480000000
b100010 #
b10001000 "
#6490000000
b10001001 "
#6500000000
b10001010 "
#6510000000
b10001011 "
#6520000000
b100011 #
b10001100 "
#6530000000
b10001101 "
#6540000000
b10001110 "
#6550000000
b10001111 "
#6560000000
b100100 #
b10010000 "
#6570000000
b10010001 "
#6580000000
b10010010 "
#6590000000
b10010011 "
#6600000000
b100101 #
b10010100 "
#6610000000
b10010101 "
#6620000000
b10010110 "
#6630000000
b10010111 "
#6640000000
b100110 #
b10011000 "
#6650000000
b10011001 "
#6660000000
b10011010 "
#6670000000
b10011011 "
#6680000000
b100111 #
b10011100 "
#6690000000
b10011101 "
#6700000000
b10011110 "
#6710000000
b10011111 "
#6720000000
b101000 #
b10100000 "
#6730000000
b10100001 "
#6740000000
b10100010 "
#6750000000
b10100011 "
#6760000000
b101001 #
b10100100 "
#6770000000
b10100101 "
#6780000000
b10100110 "
#6790000000
b10100111 "
#6800000000
b101010 #
b10101000 "
#6810000000
b10101001 "
#6820000000
b10101010 "
#6830000000
b10101011 "
#6840000000
b101011 #
b10101100 "
#6850000000
b10101101 "
#6860000000
b10101110 "
#6870000000
b10101111 "
#6880000000
b101100 #
b10110000 "
#6890000000
b10110001 "
#6900000000
b10110010 "
#6910000000
b10110011 "
#6920000000
b101101 #
b10110100 "
#6930000000
b10110101 "
#6940000000
b10110110 "
#6950000000
b10110111 "
#6960000000
b101110 #
b10111000 "
#6970000000
b10111001 "
#6980000000
b10111010 "
#6990000000
b10111011 "
#7000000000
b101111 #
b10111100 "
#7010000000
b10111101 "
#7020000000
b10111110 "
#7030000000
b10111111 "
#7040000000
b110000 #
b11000000 "
#7050000000
b11000001 "
#7060000000
b11000010 "
#7070000000
b11000011 "
#7080000000
b110001 #
b11000100 "
#7090000000
b11000101 "
#7100000000
b11000110 "
#7110000000
b11000111 "
#7120000000
b110010 #
b11001000 "
#7130000000
b11001001 "
#7140000000
b11001010 "
#7150000000
b11001011 "
#7160000000
b110011 #
b11001100 "
#7170000000
b11001101 "
#7180000000
b11001110 "
#7190000000
b11001111 "
#7200000000
b110100 #
b11010000 "
#7210000000
b11010001 "
#7220000000
b11010010 "
#7230000000
b11010011 "
#7240000000
b110101 #
b11010100 "
#7250000000
b11010101 "
#7260000000
b11010110 "
#7270000000
b11010111 "
#7280000000
b110110 #
b11011000 "
#7290000000
b11011001 "
#7300000000
b11011010 "
#7310000000
b11011011 "
#7320000000
b110111 #
b11011100 "
#7330000000
b11011101 "
#7340000000
b11011110 "
#7350000000
b11011111 "
#7360000000
b111000 #
b11100000 "
#7370000000
b11100001 "
#7380000000
b11100010 "
#7390000000
b11100011 "
#7400000000
b111001 #
b11100100 "
#7410000000
b11100101 "
#7420000000
b11100110 "
#7430000000
b11100111 "
#7440000000
b111010 #
b11101000 "
#7450000000
b11101001 "
#7460000000
b11101010 "
#7470000000
b11101011 "
#7480000000
b111011 #
b11101100 "
#7490000000
b11101101 "
#7500000000
b11101110 "
#7510000000
b11101111 "
#7520000000
b111100 #
b11110000 "
#7530000000
b11110001 "
#7540000000
b11110010 "
#7550000000
b11110011 "
#7560000000
b111101 #
b11110100 "
#7570000000
b11110101 "
#7580000000
b11110110 "
#7590000000
b11110111 "
#7600000000
b111110 #
b11111000 "
#7610000000
b11111001 "
#7620000000
b11111010 "
#7630000000
b11111011 "
#7640000000
b111111 #
b11111100 "
#7650000000
b11111101 "
#7660000000
b11111110 "
#7670000000
b11111111 "
#7680000000
b0 #
b11 !
b0 "
#7690000000
b1 "
#7700000000
b10 "
#7710000000
b11 "
#7720000000
b1 #
b100 "
#7730000000
b101 "
#7740000000
b110 "
#7750000000
b111 "
#7760000000
b11 #
b1000 "
#7770000000
b1001 "
#7780000000
b1010 "
#7790000000
b1011 "
#7800000000
b100 #
b1100 "
#7810000000
b1101 "
#7820000000
b1110 "
#7830000000
b1111 "
#7840000000
b110 #
b10000 "
#7850000000
b10001 "
#7860000000
b10010 "
#7870000000
b10011 "
#7880000000
b111 #
b10100 "
#7890000000
b10101 "
#7900000000
b10110 "
#7910000000
b10111 "
#7920000000
b1001 #
b11000 "
#7930000000
b11001 "
#7940000000
b11010 "
#7950000000
b11011 "
#7960000000
b1010 #
b11100 "
#7970000000
b11101 "
#7980000000
b11110 "
#7990000000
b11111 "
#8000000000
b1100 #
b100000 "
#8010000000
b100001 "
#8020000000
b100010 "
#8030000000
b100011 "
#8040000000
b1101 #
b100100 "
#8050000000
b100101 "
#8060000000
b100110 "
#8070000000
b100111 "
#8080000000
b1111 #
b101000 "
#8090000000
b101001 "
#8100000000
b101010 "
#8110000000
b101011 "
#8120000000
b10000 #
b101100 "
#8130000000
b101101 "
#8140000000
b101110 "
#8150000000
b101111 "
#8160000000
b10010 #
b110000 "
#8170000000
b110001 "
#8180000000
b110010 "
#8190000000
b110011 "
#8200000000
b10011 #
b110100 "
#8210000000
b110101 "
#8220000000
b110110 "
#8230000000
b110111 "
#8240000000
b10101 #
b111000 "
#8250000000
b111001 "
#8260000000
b111010 "
#8270000000
b111011 "
#8280000000
b10110 #
b111100 "
#8290000000
b111101 "
#8300000000
b111110 "
#8310000000
b111111 "
#8320000000
b11000 #
b1000000 "
#8330000000
b1000001 "
#8340000000
b1000010 "
#8350000000
b1000011 "
#8360000000
b11001 #
b1000100 "
#8370000000
b1000101 "
#8380000000
b1000110 "
#8390000000
b1000111 "
#8400000000
b11011 #
b1001000 "
#8410000000
b1001001 "
#8420000000
b1001010 "
#8430000000
b1001011 "
#8440000000
b11100 #
b1001100 "
#8450000000
b1001101 "
#8460000000
b1001110 "
#8470000000
b1001111 "
#8480000000
b11110 #
b1010000 "
#8490000000
b1010001 "
#8500000000
b1010010 "
#8510000000
b1010011 "
#8520000000
b11111 #
b1010100 "
#8530000000
b1010101 "
#8540000000
b1010110 "
#8550000000
b1010111 "
#8560000000
b100001 #
b1011000 "
#8570000000
b1011001 "
#8580000000
b1011010 "
#8590000000
b1011011 "
#8600000000
b100010 #
b1011100 "
#8610000000
b1011101 "
#8620000000
b1011110 "
#8630000000
b1011111 "
#8640000000
b100100 #
b1100000 "
#8650000000
b1100001 "
#8660000000
b1100010 "
#8670000000
b1100011 "
#8680000000
b100101 #
b1100100 "
#8690000000
b1100101 "
#8700000000
b1100110 "
#8710000000
b1100111 "
#8720000000
b100111 #
b1101000 "
#8730000000
b1101001 "
#8740000000
b1101010 "
#8750000000
b1101011 "
#8760000000
b101000 #
b1101100 "
#8770000000
b1101101 "
#8780000000
b1101110 "
#8790000000
b1101111 "
#8800000000
b101010 #
b1110000 "
#8810000000
b1110001 "
#8820000000
b1110010 "
#8830000000
b1110011 "
#8840000000
b101011 #
b1110100 "
#8850000000
b1110101 "
#8860000000
b1110110 "
#8870000000
b1110111 "
#8880000000
b101101 #
b1111000 "
#8890000000
b1111001 "
#8900000000
b1111010 "
#8910000000
b1111011 "
#8920000000
b101110 #
b1111100 "
#8930000000
b1111101 "
#8940000000
b1111110 "
#8950000000
b1111111 "
#8960000000
b110000 #
b10000000 "
#8970000000
b10000001 "
#8980000000
b10000010 "
#8990000000
b10000011 "
#9000000000
b110001 #
b10000100 "
#9010000000
b10000101 "
#9020000000
b10000110 "
#9030000000
b10000111 "
#9040000000
b110011 #
b10001000 "
#9050000000
b10001001 "
#9060000000
b10001010 "
#9070000000
b10001011 "
#9080000000
b110100 #
b10001100 "
#9090000000
b10001101 "
#9100000000
b10001110 "
#9110000000
b10001111 "
#9120000000
b110110 #
b10010000 "
#9130000000
b10010001 "
#9140000000
b10010010 "
#9150000000
b10010011 "
#9160000000
b110111 #
b10010100 "
#9170000000
b10010101 "
#9180000000
b10010110 "
#9190000000
b10010111 "
#9200000000
b111001 #
b10011000 "
#9210000000
b10011001 "
#9220000000
b10011010 "
#9230000000
b10011011 "
#9240000000
b111010 #
b10011100 "
#9250000000
b10011101 "
#9260000000
b10011110 "
#9270000000
b10011111 "
#9280000000
b111100 #
b10100000 "
#9290000000
b10100001 "
#9300000000
b10100010 "
#9310000000
b10100011 "
#9320000000
b111101 #
b10100100 "
#9330000000
b10100101 "
#9340000000
b10100110 "
#9350000000
b10100111 "
#9360000000
b111111 #
b10101000 "
#9370000000
b10101001 "
#9380000000
b10101010 "
#9390000000
b10101011 "
#9400000000
b1000000 #
b10101100 "
#9410000000
b10101101 "
#9420000000
b10101110 "
#9430000000
b10101111 "
#9440000000
b1000010 #
b10110000 "
#9450000000
b10110001 "
#9460000000
b10110010 "
#9470000000
b10110011 "
#9480000000
b1000011 #
b10110100 "
#9490000000
b10110101 "
#9500000000
b10110110 "
#9510000000
b10110111 "
#9520000000
b1000101 #
b10111000 "
#9530000000
b10111001 "
#9540000000
b10111010 "
#9550000000
b10111011 "
#9560000000
b1000110 #
b10111100 "
#9570000000
b10111101 "
#9580000000
b10111110 "
#9590000000
b10111111 "
#9600000000
b1001000 #
b11000000 "
#9610000000
b11000001 "
#9620000000
b11000010 "
#9630000000
b11000011 "
#9640000000
b1001001 #
b11000100 "
#9650000000
b11000101 "
#9660000000
b11000110 "
#9670000000
b11000111 "
#9680000000
b1001011 #
b11001000 "
#9690000000
b11001001 "
#9700000000
b11001010 "
#9710000000
b11001011 "
#9720000000
b1001100 #
b11001100 "
#9730000000
b11001101 "
#9740000000
b11001110 "
#9750000000
b11001111 "
#9760000000
b1001110 #
b11010000 "
#9770000000
b11010001 "
#9780000000
b11010010 "
#9790000000
b11010011 "
#9800000000
b1001111 #
b11010100 "
#9810000000
b11010101 "
#9820000000
b11010110 "
#9830000000
b11010111 "
#9840000000
b1010001 #
b11011000 "
#9850000000
b11011001 "
#9860000000
b11011010 "
#9870000000
b11011011 "
#9880000000
b1010010 #
b11011100 "
#9890000000
b11011101 "
#9900000000
b11011110 "
#9910000000
b11011111 "
#9920000000
b1010100 #
b11100000 "
#9930000000
b11100001 "
#9940000000
b11100010 "
#9950000000
b11100011 "
#9960000000
b1010101 #
b11100100 "
#9970000000
b11100101 "
#9980000000
b11100110 "
#9990000000
b11100111 "
#10000000000
b1010111 #
b11101000 "
#10010000000
b11101001 "
#10020000000
b11101010 "
#10030000000
b11101011 "
#10040000000
b1011000 #
b11101100 "
#10050000000
b11101101 "
#10060000000
b11101110 "
#10070000000
b11101111 "
#10080000000
b1011010 #
b11110000 "
#10090000000
b11110001 "
#10100000000
b11110010 "
#10110000000
b11110011 "
#10120000000
b1011011 #
b11110100 "
#10130000000
b11110101 "
#10140000000
b11110110 "
#10150000000
b11110111 "
#10160000000
b1011101 #
b11111000 "
#10170000000
b11111001 "
#10180000000
b11111010 "
#10190000000
b11111011 "
#10200000000
b1011110 #
b11111100 "
#10210000000
b11111101 "
#10220000000
b11111110 "
#10230000000
b11111111 "
#10240000000
b0 #
b100 !
b0 "
#10250000000
b1 "
#10260000000
b1 #
b10 "
#10270000000
b11 "
#10280000000
b10 #
b100 "
#10290000000
b101 "
#10300000000
b11 #
b110 "
#10310000000
b111 "
#10320000000
b100 #
b1000 "
#10330000000
b1001 "
#10340000000
b101 #
b1010 "
#10350000000
b1011 "
#10360000000
b110 #
b1100 "
#10370000000
b1101 "
#10380000000
b111 #
b1110 "
#10390000000
b1111 "
#10400000000
b1000 #
b10000 "
#10410000000
b10001 "
#10420000000
b1001 #
b10010 "
#10430000000
b10011 "
#10440000000
b1010 #
b10100 "
#10450000000
b10101 "
#10460000000
b1011 #
b10110 "
#10470000000
b10111 "
#10480000000
b1100 #
b11000 "
#10490000000
b11001 "
#10500000000
b1101 #
b11010 "
#10510000000
b11011 "
#10520000000
b1110 #
b11100 "
#10530000000
b11101 "
#10540000000
b1111 #
b11110 "
