verilog-workbench/src/sram.v
`default_nettype none
`timescale 1ns/1ns

`define SIZE 512
`define WIDTH 32
`define WRITABLE 1
// `define WRITE_WIDTH 32

module sram (
    `ifdef WRITABLE
        input wire [`WIDTH-1:0] write_data,
        input wire [11:0] write_addr,
        input wire we,
    `endif
    output reg [`WIDTH-1:0] read_data,
    input wire [11:0] read_addr,
    input wire clk
    );
    parameter T_HOLD = 2000 ; //Delay to hold dout value after posedge. Value is arbitrary

    `ifdef WRITABLE
        reg [11:0] write_addr_reg;
        reg [`WIDTH-1:0] write_data_reg;
        reg we_reg;
    `endif
    
    initial begin
        clk2 <= 0;
    end
    reg clk2;
    always @(posedge clk) begin
        clk2 <= !clk2;
    end
    
    reg [11:0] read_addr_reg;
    reg [`WIDTH-1:0] mem_array [`SIZE-1:0];

    always @(posedge clk) begin
        read_addr_reg <= read_addr;
        #(T_HOLD) read_data <= 32'bx;
        `ifdef WRITABLE
            write_addr_reg <= write_addr;
            write_data_reg <= write_data;
            we_reg <= we;
        `endif
    end

    `ifdef WRITABLE
    always @(negedge clk) begin
        if (we) begin
            mem_array[write_addr_reg] <= write_data_reg;
        end
    end
    `endif

    always @(negedge clk) begin
        read_data <= mem_array[read_addr_reg];
    end

    `ifdef COCOTB_SIM 
    initial begin
    $dumpfile ("sram.vcd");
    $dumpvars (0, sram);
    #1;
    end
    `endif

endmodule

verilog-workbench/sram.vcd
$date
	Wed Sep 21 19:58:59 2022
$end
$version
	Icarus Verilog
$end
$timescale
	1ps
$end
$scope module sram $end
$var wire 1 ! clk $end
$var wire 12 " read_addr [11:0] $end
$var wire 1 # we $end
$var wire 12 $ write_addr [11:0] $end
$var wire 32 % write_data [31:0] $end
$var reg 1 & clk2 $end
$var reg 12 ' read_addr_reg [11:0] $end
$var reg 32 ( read_data [31:0] $end
$var reg 1 ) we_reg $end
$var reg 12 * write_addr_reg [11:0] $end
$var reg 32 + write_data_reg [31:0] $end
$upscope $end
$enddefinitions $end
#0
$dumpvars
bx +
bx *
x)
bx (
bz '
1&
b0 %
b0 $
1#
bz "
1!
$end
#2000000
1)
b0 +
b0 *
#5000000
0!
#10000000
0&
1!
#15000000
0!
#20000000
0#
b0 "
1&
1!
#22000000
0)
#25000000
0!
#30000000
0&
b0 '
1!
#35000000
b0 (
0!
#40000000
1#
b1 $
1&
1!
#42000000
1)
b1 *
bx (
#45000000
b0 (
0!
#50000000
0&
1!
#52000000
bx (
#55000000
b0 (
0!
#60000000
0#
b1 "
1&
1!
#62000000
0)
bx (
#65000000
b0 (
0!
#70000000
0&
b1 '
1!
#72000000
bx (
#75000000
b0 (
0!
#80000000
1#
b10 $
1&
1!
#82000000
1)
b10 *
bx (
#85000000
b0 (
0!
#90000000
0&
1!
#92000000
bx (
#95000000
b0 (
0!
#100000000
0#
b10 "
1&
1!
#102000000
0)
bx (
#105000000
b0 (
0!
#110000000
0&
b10 '
1!
#112000000
bx (
#115000000
b0 (
0!
#120000000
1#
b11 $
1&
1!
#122000000
1)
b11 *
bx (
#125000000
b0 (
0!
#130000000
0&
1!
#132000000
bx (
#135000000
b0 (
0!
#140000000
0#
b11 "
1&
1!
#142000000
0)
bx (
#145000000
b0 (
0!
#150000000
0&
b11 '
1!
#152000000
bx (
#155000000
b0 (
0!
#160000000
1#
b100 $
1&
1!
#162000000
1)
b100 *
bx (
#165000000
b0 (
0!
#170000000
0&
1!
#172000000
bx (
#175000000
b0 (
0!
#180000000
0#
b100 "
1&
1!
#182000000
0)
bx (
#185000000
b0 (
0!
#190000000
0&
b100 '
1!
#192000000
bx (
#195000000
b0 (
0!
#200000000
1#
b101 $
1&
1!
#202000000
1)
b101 *
bx (
#205000000
b0 (
0!
#210000000
0&
1!
#212000000
bx (
#215000000
b0 (
0!
#220000000
0#
b101 "
1&
1!
#222000000
0)
bx (
#225000000
b0 (
0!
#230000000
0&
b101 '
1!
#232000000
bx (
#235000000
b0 (
0!
#240000000
1#
b110 $
1&
1!
#242000000
1)
b110 *
bx (
#245000000
b0 (
0!
#250000000
0&
1!
#252000000
bx (
#255000000
b0 (
0!
#260000000
0#
b110 "
1&
1!
#262000000
0)
bx (
#265000000
b0 (
0!
#270000000
0&
b110 '
1!
#272000000
bx (
#275000000
b0 (
0!
#280000000
1#
b111 $
1&
1!
#282000000
1)
b111 *
bx (
#285000000
b0 (
0!
#290000000
0&
1!
#292000000
bx (
#295000000
b0 (
0!
#300000000
0#
b111 "
1&
1!
#302000000
0)
bx (
#305000000
b0 (
0!
#310000000
0&
b111 '
1!
#312000000
bx (
#315000000
b0 (
0!
#320000000
1#
b1000 $
1&
1!
#322000000
1)
b1000 *
bx (
#325000000
b0 (
0!
#330000000
0&
1!
#332000000
bx (
#335000000
b0 (
0!
#340000000
0#
b1000 "
1&
1!
#342000000
0)
bx (
#345000000
b0 (
0!
#350000000
0&
b1000 '
1!
#352000000
bx (
#355000000
b0 (
0!
#360000000
1#
b1001 $
1&
1!
#362000000
1)
b1001 *
bx (
#365000000
b0 (
0!
#370000000
0&
1!
#372000000
bx (
#375000000
b0 (
0!
#380000000
0#
b1001 "
1&
1!
#382000000
0)
bx (
#385000000
b0 (
0!
#390000000
0&
b1001 '
1!
#392000000
bx (
#395000000
b0 (
0!
#400000000
1#
b1010 $
1&
1!
#402000000
1)
b1010 *
bx (
#405000000
b0 (
0!
#410000000
0&
1!
#412000000
bx (
#415000000
b0 (
0!
#420000000
0#
b1010 "
1&
1!
#422000000
0)
bx (
#425000000
b0 (
0!
#430000000
0&
b1010 '
1!
#432000000
bx (
#435000000
b0 (
0!
#440000000
1#
b1011 $
1&
1!
#442000000
1)
b1011 *
bx (
#445000000
b0 (
0!
#450000000
0&
1!
#452000000
bx (
#455000000
b0 (
0!
#460000000
0#
b1011 "
1&
1!
#462000000
0)
bx (
#465000000
b0 (
0!
#470000000
0&
b1011 '
1!
#472000000
bx (
#475000000
b0 (
0!
#480000000
1#
b1100 $
1&
1!
#482000000
1)
b1100 *
bx (
#485000000
b0 (
0!
#490000000
0&
1!
#492000000
bx (
#495000000
b0 (
0!
#500000000
0#
b1100 "
1&
1!
#502000000
0)
bx (
#505000000
b0 (
0!
#510000000
0&
b1100 '
1!
#512000000
bx (
#515000000
b0 (
0!
#520000000
1#
b1101 $
1&
1!
#522000000
1)
b1101 *
bx (
#525000000
b0 (
0!
#530000000
0&
1!
#532000000
bx (
#535000000
b0 (
0!
#540000000
0#
b1101 "
1&
1!
#542000000
0)
bx (
#545000000
b0 (
0!
#550000000
0&
b1101 '
1!
#552000000
bx (
#555000000
b0 (
0!
#560000000
1#
b1110 $
1&
1!
#562000000
1)
b1110 *
bx (
#565000000
b0 (
0!
#570000000
0&
1!
#572000000
bx (
#575000000
b0 (
0!
#580000000
0#
b1110 "
1&
1!
#582000000
0)
bx (
#585000000
b0 (
0!
#590000000
0&
b1110 '
1!
#592000000
bx (
#595000000
b0 (
0!
#600000000
1#
b1111 $
1&
1!
#602000000
1)
b1111 *
bx (
#605000000
b0 (
0!
#610000000
0&
1!
#612000000
bx (
#615000000
b0 (
0!
#620000000
0#
b1111 "
1&
1!
#622000000
0)
bx (
#625000000
b0 (
0!
#630000000
0&
b1111 '
1!
#632000000
bx (
#635000000
b0 (
0!
#640000000
1#
b10000 $
1&
1!
#642000000
1)
b10000 *
bx (
#645000000
b0 (
0!
#650000000
0&
1!
#652000000
bx (
#655000000
b0 (
0!
#660000000
0#
b10000 "
1&
1!
#662000000
0)
bx (
#665000000
b0 (
0!
#670000000
0&
b10000 '
1!
#672000000
bx (
#675000000
b0 (
0!
#680000000
1#
b10001 $
1&
1!
#682000000
1)
b10001 *
bx (
#685000000
b0 (
0!
#690000000
0&
1!
#692000000
bx (
#695000000
b0 (
0!
#700000000
0#
b10001 "
1&
1!
#702000000
0)
bx (
#705000000
b0 (
0!
#710000000
0&
b10001 '
1!
#712000000
bx (
#715000000
b0 (
0!
#720000000
1#
b10010 $
1&
1!
#722000000
1)
b10010 *
bx (
#725000000
b0 (
0!
#730000000
0&
1!
#732000000
bx (
#735000000
b0 (
0!
#740000000
0#
b10010 "
1&
1!
#742000000
0)
bx (
#745000000
b0 (
0!
#750000000
0&
b10010 '
1!
#752000000
bx (
#755000000
b0 (
0!
#760000000
1#
b10011 $
1&
1!
#762000000
1)
b10011 *
bx (
#765000000
b0 (
0!
#770000000
0&
1!
#772000000
bx (
#775000000
b0 (
0!
#780000000
0#
b10011 "
1&
1!
#782000000
0)
bx (
#785000000
b0 (
0!
#790000000
0&
b10011 '
1!
#792000000
bx (
#795000000
b0 (
0!
#800000000
1#
b10100 $
1&
1!
#802000000
1)
b10100 *
bx (
#805000000
b0 (
0!
#810000000
0&
1!
#812000000
bx (
#815000000
b0 (
0!
#820000000
0#
b10100 "
1&
1!
#822000000
0)
bx (
#825000000
b0 (
0!
#830000000
0&
b10100 '
1!
#832000000
bx (
#835000000
b0 (
0!
#840000000
1#
b10101 $
1&
1!
#842000000
1)
b10101 *
bx (
#845000000
b0 (
0!
#850000000
0&
1!
#852000000
bx (
#855000000
b0 (
0!
#860000000
0#
b10101 "
1&
1!
#862000000
0)
bx (
#865000000
b0 (
0!
#870000000
0&
b10101 '
1!
#872000000
bx (
#875000000
b0 (
0!
#880000000
1#
b10110 $
1&
1!
#882000000
1)
b10110 *
bx (
#885000000
b0 (
0!
#890000000
0&
1!
#892000000
bx (
#895000000
b0 (
0!
#900000000
0#
b10110 "
1&
1!
#902000000
0)
bx (
#905000000
b0 (
0!
#910000000
0&
b10110 '
1!
#912000000
bx (
#915000000
b0 (
0!
#920000000
1#
b10111 $
1&
1!
#922000000
1)
b10111 *
bx (
#925000000
b0 (
0!
#930000000
0&
1!
#932000000
bx (
#935000000
b0 (
0!
#940000000
0#
b10111 "
1&
1!
#942000000
0)
bx (
#945000000
b0 (
0!
#950000000
0&
b10111 '
1!
#952000000
bx (
#955000000
b0 (
0!
#960000000
1#
b11000 $
1&
1!
#962000000
1)
b11000 *
bx (
#965000000
b0 (
0!
#970000000
0&
1!
#972000000
bx (
#975000000
b0 (
0!
#980000000
0#
b11000 "
1&
1!
#982000000
0)
bx (
#985000000
b0 (
0!
#990000000
0&
b11000 '
1!
#992000000
bx (
#995000000
b0 (
0!
#1000000000
1#
b11001 $
1&
1!
#1002000000
1)
b11001 *
bx (
#1005000000
b0 (
0!
#1010000000
0&
1!
#1012000000
bx (
#1015000000
b0 (
0!
#1020000000
0#
b11001 "
1&
1!
#1022000000
0)
bx (
#1025000000
b0 (
0!
#1030000000
0&
b11001 '
1!
#1032000000
bx (
#1035000000
b0 (
0!
#1040000000
1#
b11010 $
1&
1!
#1042000000
1)
b11010 *
bx (
#1045000000
b0 (
0!
#1050000000
0&
1!
#1052000000
bx (
#1055000000
b0 (
0!
#1060000000
0#
b11010 "
1&
1!
#1062000000
0)
bx (
#1065000000
b0 (
0!
#1070000000
0&
b11010 '
1!
#1072000000
bx (
#1075000000
b0 (
0!
#1080000000
1#
b11011 $
1&
1!
#1082000000
1)
b11011 *
bx (
#1085000000
b0 (
0!
#1090000000
0&
1!
#1092000000
bx (
#1095000000
b0 (
0!
#1100000000
0#
b11011 "
1&
1!
#1102000000
0)
bx (
#1105000000
b0 (
0!
#1110000000
0&
b11011 '
1!
#1112000000
bx (
#1115000000
b0 (
0!
#1120000000
1#
b11100 $
1&
1!
#1122000000
1)
b11100 *
bx (
#1125000000
b0 (
0!
#1130000000
0&
1!
#1132000000
bx (
#1135000000
b0 (
0!
#1140000000
0#
b11100 "
1&
1!
#1142000000
0)
bx (
#1145000000
b0 (
0!
#1150000000
0&
b11100 '
1!
#1152000000
bx (
#1155000000
b0 (
0!
#1160000000
1#
b11101 $
1&
1!
#1162000000
1)
b11101 *
bx (
#1165000000
b0 (
0!
#1170000000
0&
1!
#1172000000
bx (
#1175000000
b0 (
0!
#1180000000
0#
b11101 "
1&
1!
#1182000000
0)
bx (
#1185000000
b0 (
0!
#1190000000
0&
b11101 '
1!
#1192000000
bx (
#1195000000
b0 (
0!
#1200000000
1#
b11110 $
1&
1!
#1202000000
1)
b11110 *
bx (
#1205000000
b0 (
0!
#1210000000
0&
1!
#1212000000
bx (
#1215000000
b0 (
0!
#1220000000
0#
b11110 "
1&
1!
#1222000000
0)
bx (
#1225000000
b0 (
0!
#1230000000
0&
b11110 '
1!
#1232000000
bx (
#1235000000
b0 (
0!
#1240000000
1#
b11111 $
1&
1!
#1242000000
1)
b11111 *
bx (
#1245000000
b0 (
0!
#1250000000
0&
1!
#1252000000
bx (
#1255000000
b0 (
0!
#1260000000
0#
b11111 "
1&
1!
#1262000000
0)
bx (
#1265000000
b0 (
0!
#1270000000
0&
b11111 '
1!
#1272000000
bx (
#1275000000
b0 (
0!
#1280000000
1#
b100000 $
1&
1!
#1282000000
1)
b100000 *
bx (
#1285000000
b0 (
0!
#1290000000
0&
1!
#1292000000
bx (
#1295000000
b0 (
0!
#1300000000
0#
b100000 "
1&
1!
#1302000000
0)
bx (
#1305000000
b0 (
0!
#1310000000
0&
b100000 '
1!
#1312000000
bx (
#1315000000
b0 (
0!
#1320000000
1#
b100001 $
1&
1!
#1322000000
1)
b100001 *
bx (
#1325000000
b0 (
0!
#1330000000
0&
1!
#1332000000
bx (
#1335000000
b0 (
0!
#1340000000
0#
b100001 "
1&
1!
#1342000000
0)
bx (
#1345000000
b0 (
0!
#1350000000
0&
b100001 '
1!
#1352000000
bx (
#1355000000
b0 (
0!
#1360000000
1#
b100010 $
1&
1!
#1362000000
1)
b100010 *
bx (
#1365000000
b0 (
0!
#1370000000
0&
1!
#1372000000
bx (
#1375000000
b0 (
0!
#1380000000
0#
b100010 "
1&
1!
#1382000000
0)
bx (
#1385000000
b0 (
0!
#1390000000
0&
b100010 '
1!
#1392000000
bx (
#1395000000
b0 (
0!
#1400000000
1#
b100011 $
1&
1!
#1402000000
1)
b100011 *
bx (
#1405000000
b0 (
0!
#1410000000
0&
1!
#1412000000
bx (
#1415000000
b0 (
0!
#1420000000
0#
b100011 "
1&
1!
#1422000000
0)
bx (
#1425000000
b0 (
0!
#1430000000
0&
b100011 '
1!
#1432000000
bx (
#1435000000
b0 (
0!
#1440000000
1#
b100100 $
1&
1!
#1442000000
1)
b100100 *
bx (
#1445000000
b0 (
0!
#1450000000
0&
1!
#1452000000
bx (
#1455000000
b0 (
0!
#1460000000
0#
b100100 "
1&
1!
#1462000000
0)
bx (
#1465000000
b0 (
0!
#1470000000
0&
b100100 '
1!
#1472000000
bx (
#1475000000
b0 (
0!
#1480000000
1#
b100101 $
1&
1!
#1482000000
1)
b100101 *
bx (
#1485000000
b0 (
0!
#1490000000
0&
1!
#1492000000
bx (
#1495000000
b0 (
0!
#1500000000
0#
b100101 "
1&
1!
#1502000000
0)
bx (
#1505000000
b0 (
0!
#1510000000
0&
b100101 '
1!
#1512000000
bx (
#1515000000
b0 (
0!
#1520000000
1#
b100110 $
1&
1!
#1522000000
1)
b100110 *
bx (
#1525000000
b0 (
0!
#1530000000
0&
1!
#1532000000
bx (
#1535000000
b0 (
0!
#1540000000
0#
b100110 "
1&
1!
#1542000000
0)
bx (
#1545000000
b0 (
0!
#1550000000
0&
b100110 '
1!
#1552000000
bx (
#1555000000
b0 (
0!
#1560000000
1#
b100111 $
1&
1!
#1562000000
1)
b100111 *
bx (
#1565000000
b0 (
0!
#1570000000
0&
1!
#1572000000
bx (
#1575000000
b0 (
0!
#1580000000
0#
b100111 "
1&
1!
#1582000000
0)
bx (
#1585000000
b0 (
0!
#1590000000
0&
b100111 '
1!
#1592000000
bx (
#1595000000
b0 (
0!
#1600000000
1#
b101000 $
1&
1!
#1602000000
1)
b101000 *
bx (
#1605000000
b0 (
0!
#1610000000
0&
1!
#1612000000
bx (
#1615000000
b0 (
0!
#1620000000
0#
b101000 "
1&
1!
#1622000000
0)
bx (
#1625000000
b0 (
0!
#1630000000
0&
b101000 '
1!
#1632000000
bx (
#1635000000
b0 (
0!
#1640000000
1#
b101001 $
1&
1!
#1642000000
1)
b101001 *
bx (
#1645000000
b0 (
0!
#1650000000
0&
1!
#1652000000
bx (
#1655000000
b0 (
0!
#1660000000
0#
b101001 "
1&
1!
#1662000000
0)
bx (
#1665000000
b0 (
0!
#1670000000
0&
b101001 '
1!
#1672000000
bx (
#1675000000
b0 (
0!
#1680000000
1#
b101010 $
1&
1!
#1682000000
1)
b101010 *
bx (
#1685000000
b0 (
0!
#1690000000
0&
1!
#1692000000
bx (
#1695000000
b0 (
0!
#1700000000
0#
b101010 "
1&
1!
#1702000000
0)
bx (
#1705000000
b0 (
0!
#1710000000
0&
b101010 '
1!
#1712000000
bx (
#1715000000
b0 (
0!
#1720000000
1#
b101011 $
1&
1!
#1722000000
1)
b101011 *
bx (
#1725000000
b0 (
0!
#1730000000
0&
1!
#1732000000
bx (
#1735000000
b0 (
0!
#1740000000
0#
b101011 "
1&
1!
#1742000000
0)
bx (
#1745000000
b0 (
0!
#1750000000
0&
b101011 '
1!
#1752000000
bx (
#1755000000
b0 (
0!
#1760000000
1#
b101100 $
1&
1!
#1762000000
1)
b101100 *
bx (
#1765000000
b0 (
0!
#1770000000
0&
1!
#1772000000
bx (
#1775000000
b0 (
0!
#1780000000
0#
b101100 "
1&
1!
#1782000000
0)
bx (
#1785000000
b0 (
0!
#1790000000
0&
b101100 '
1!
#1792000000
bx (
#1795000000
b0 (
0!
#1800000000
1#
b101101 $
1&
1!
#1802000000
1)
b101101 *
bx (
#1805000000
b0 (
0!
#1810000000
0&
1!
#1812000000
bx (
#1815000000
b0 (
0!
#1820000000
0#
b101101 "
1&
1!
#1822000000
0)
bx (
#1825000000
b0 (
0!
#1830000000
0&
b101101 '
1!
#1832000000
bx (
#1835000000
b0 (
0!
#1840000000
1#
b101110 $
1&
1!
#1842000000
1)
b101110 *
bx (
#1845000000
b0 (
0!
#1850000000
0&
1!
#1852000000
bx (
#1855000000
b0 (
0!
#1860000000
0#
b101110 "
1&
1!
#1862000000
0)
bx (
#1865000000
b0 (
0!
#1870000000
0&
b101110 '
1!
#1872000000
bx (
#1875000000
b0 (
0!
#1880000000
1#
b101111 $
1&
1!
#1882000000
1)
b101111 *
bx (
#1885000000
b0 (
0!
#1890000000
0&
1!
#1892000000
bx (
#1895000000
b0 (
0!
#1900000000
0#
b101111 "
1&
1!
#1902000000
0)
bx (
#1905000000
b0 (
0!
#1910000000
0&
b101111 '
1!
#1912000000
bx (
#1915000000
b0 (
0!
#1920000000
1#
b110000 $
1&
1!
#1922000000
1)
b110000 *
bx (
#1925000000
b0 (
0!
#1930000000
0&
1!
#1932000000
bx (
#1935000000
b0 (
0!
#1940000000
0#
b110000 "
1&
1!
#1942000000
0)
bx (
#1945000000
b0 (
0!
#1950000000
0&
b110000 '
1!
#1952000000
bx (
#1955000000
b0 (
0!
#1960000000
1#
b110001 $
1&
1!
#1962000000
1)
b110001 *
bx (
#1965000000
b0 (
0!
#1970000000
0&
1!
#1972000000
bx (
#1975000000
b0 (
0!
#1980000000
0#
b110001 "
1&
1!
#1982000000
0)
bx (
#1985000000
b0 (
0!
#1990000000
0&
b110001 '
1!
#1992000000
bx (
#1995000000
b0 (
0!
#2000000000
1#
b110010 $
1&
1!
#2002000000
1)
b110010 *
bx (
#2005000000
b0 (
0!
#2010000000
0&
1!
#2012000000
bx (
#2015000000
b0 (
0!
#2020000000
0#
b110010 "
1&
1!
#2022000000
0)
bx (
#2025000000
b0 (
0!
#2030000000
0&
b110010 '
1!
#2032000000
bx (
#2035000000
b0 (
0!
#2040000000
1#
b110011 $
1&
1!
#2042000000
1)
b110011 *
bx (
#2045000000
b0 (
0!
#2050000000
0&
1!
#2052000000
bx (
#2055000000
b0 (
0!
#2060000000
0#
b110011 "
1&
1!
#2062000000
0)
bx (
#2065000000
b0 (
0!
#2070000000
0&
b110011 '
1!
#2072000000
bx (
#2075000000
b0 (
0!
#2080000000
1#
b110100 $
1&
1!
#2082000000
1)
b110100 *
bx (
#2085000000
b0 (
0!
#2090000000
0&
1!
#2092000000
bx (
#2095000000
b0 (
0!
#2100000000
0#
b110100 "
1&
1!
#2102000000
0)
bx (
#2105000000
b0 (
0!
#2110000000
0&
b110100 '
1!
#2112000000
bx (
#2115000000
b0 (
0!
#2120000000
1#
b110101 $
1&
1!
#2122000000
1)
b110101 *
bx (
#2125000000
b0 (
0!
#2130000000
0&
1!
#2132000000
bx (
#2135000000
b0 (
0!
#2140000000
0#
b110101 "
1&
1!
#2142000000
0)
bx (
#2145000000
b0 (
0!
#2150000000
0&
b110101 '
1!
#2152000000
bx (
#2155000000
b0 (
0!
#2160000000
1#
b110110 $
1&
1!
#2162000000
1)
b110110 *
bx (
#2165000000
b0 (
0!
#2170000000
0&
1!
#2172000000
bx (
#2175000000
b0 (
0!
#2180000000
0#
b110110 "
1&
1!
#2182000000
0)
bx (
#2185000000
b0 (
0!
#2190000000
0&
b110110 '
1!
#2192000000
bx (
#2195000000
b0 (
0!
#2200000000
1#
b110111 $
1&
1!
#2202000000
1)
b110111 *
bx (
#2205000000
b0 (
0!
#2210000000
0&
1!
#2212000000
bx (
#2215000000
b0 (
0!
#2220000000
0#
b110111 "
1&
1!
#2222000000
0)
bx (
#2225000000
b0 (
0!
#2230000000
0&
b110111 '
1!
#2232000000
bx (
#2235000000
b0 (
0!
#2240000000
1#
b111000 $
1&
1!
#2242000000
1)
b111000 *
bx (
#2245000000
b0 (
0!
#2250000000
0&
1!
#2252000000
bx (
#2255000000
b0 (
0!
#2260000000
0#
b111000 "
1&
1!
#2262000000
0)
bx (
#2265000000
b0 (
0!
#2270000000
0&
b111000 '
1!
#2272000000
bx (
#2275000000
b0 (
0!
#2280000000
1#
b111001 $
1&
1!
#2282000000
1)
b111001 *
bx (
#2285000000
b0 (
0!
#2290000000
0&
1!
#2292000000
bx (
#2295000000
b0 (
0!
#2300000000
0#
b111001 "
1&
1!
#2302000000
0)
bx (
#2305000000
b0 (
0!
#2310000000
0&
b111001 '
1!
#2312000000
bx (
#2315000000
b0 (
0!
#2320000000
1#
b111010 $
1&
1!
#2322000000
1)
b111010 *
bx (
#2325000000
b0 (
0!
#2330000000
0&
1!
#2332000000
bx (
#2335000000
b0 (
0!
#2340000000
0#
b111010 "
1&
1!
#2342000000
0)
bx (
#2345000000
b0 (
0!
#2350000000
0&
b111010 '
1!
#2352000000
bx (
#2355000000
b0 (
0!
#2360000000
1#
b111011 $
1&
1!
#2362000000
1)
b111011 *
bx (
#2365000000
b0 (
0!
#2370000000
0&
1!
#2372000000
bx (
#2375000000
b0 (
0!
#2380000000
0#
b111011 "
1&
1!
#2382000000
0)
bx (
#2385000000
b0 (
0!
#2390000000
0&
b111011 '
1!
#2392000000
bx (
#2395000000
b0 (
0!
#2400000000
1#
b111100 $
1&
1!
#2402000000
1)
b111100 *
bx (
#2405000000
b0 (
0!
#2410000000
0&
1!
#2412000000
bx (
#2415000000
b0 (
0!
#2420000000
0#
b111100 "
1&
1!
#2422000000
0)
bx (
#2425000000
b0 (
0!
#2430000000
0&
b111100 '
1!
#2432000000
bx (
#2435000000
b0 (
0!
#2440000000
1#
b111101 $
1&
1!
#2442000000
1)
b111101 *
bx (
#2445000000
b0 (
0!
#2450000000
0&
1!
#2452000000
bx (
#2455000000
b0 (
0!
#2460000000
0#
b111101 "
1&
1!
#2462000000
0)
bx (
#2465000000
b0 (
0!
#2470000000
0&
b111101 '
1!
#2472000000
bx (
#2475000000
b0 (
0!
#2480000000
1#
b111110 $
1&
1!
#2482000000
1)
b111110 *
bx (
#2485000000
b0 (
0!
#2490000000
0&
1!
#2492000000
bx (
#2495000000
b0 (
0!
#2500000000
0#
b111110 "
1&
1!
#2502000000
0)
bx (
#2505000000
b0 (
0!
#2510000000
0&
b111110 '
1!
#2512000000
bx (
#2515000000
b0 (
0!
#2520000000
1#
b111111 $
1&
1!
#2522000000
1)
b111111 *
bx (
#2525000000
b0 (
0!
#2530000000
0&
1!
#2532000000
bx (
#2535000000
b0 (
0!
#2540000000
0#
b111111 "
1&
1!
#2542000000
0)
bx (
#2545000000
b0 (
0!
#2550000000
0&
b111111 '
1!
#2552000000
bx (
#2555000000
b0 (
0!
#2560000000
1#
b1000000 $
1&
1!
#2562000000
1)
b1000000 *
bx (
#2565000000
b0 (
0!
#2570000000
0&
1!
#2572000000
bx (
#2575000000
b0 (
0!
#2580000000
0#
b1000000 "
1&
1!
#2582000000
0)
bx (
#2585000000
b0 (
0!
#2590000000
0&
b1000000 '
1!
#2592000000
bx (
#2595000000
b0 (
0!
#2600000000
1#
b1000001 $
1&
1!
#2602000000
1)
b1000001 *
bx (
#2605000000
b0 (
0!
#2610000000
0&
1!
#2612000000
bx (
#2615000000
b0 (
0!
#2620000000
0#
b1000001 "
1&
1!
#2622000000
0)
bx (
#2625000000
b0 (
0!
#2630000000
0&
b1000001 '
1!
#2632000000
bx (
#2635000000
b0 (
0!
#2640000000
1#
b1000010 $
1&
1!
#2642000000
1)
b1000010 *
bx (
#2645000000
b0 (
0!
#2650000000
0&
1!
#2652000000
bx (
#2655000000
b0 (
0!
#2660000000
0#
b1000010 "
1&
1!
#2662000000
0)
bx (
#2665000000
b0 (
0!
#2670000000
0&
b1000010 '
1!
#2672000000
bx (
#2675000000
b0 (
0!
#2680000000
1#
b1000011 $
1&
1!
#2682000000
1)
b1000011 *
bx (
#2685000000
b0 (
0!
#2690000000
0&
1!
#2692000000
bx (
#2695000000
b0 (
0!
#2700000000
0#
b1000011 "
1&
1!
#2702000000
0)
bx (
#2705000000
b0 (
0!
#2710000000
0&
b1000011 '
1!
#2712000000
bx (
#2715000000
b0 (
0!
#2720000000
1#
b1000100 $
1&
1!
#2722000000
1)
b1000100 *
bx (
#2725000000
b0 (
0!
#2730000000
0&
1!
#2732000000
bx (
#2735000000
b0 (
0!
#2740000000
0#
b1000100 "
1&
1!
#2742000000
0)
bx (
#2745000000
b0 (
0!
#2750000000
0&
b1000100 '
1!
#2752000000
bx (
#2755000000
b0 (
0!
#2760000000
1#
b1000101 $
1&
1!
#2762000000
1)
b1000101 *
bx (
#2765000000
b0 (
0!
#2770000000
0&
1!
#2772000000
bx (
#2775000000
b0 (
0!
#2780000000
0#
b1000101 "
1&
1!
#2782000000
0)
bx (
#2785000000
b0 (
0!
#2790000000
0&
b1000101 '
1!
#2792000000
bx (
#2795000000
b0 (
0!
#2800000000
1#
b1000110 $
1&
1!
#2802000000
1)
b1000110 *
bx (
#2805000000
b0 (
0!
#2810000000
0&
1!
#2812000000
bx (
#2815000000
b0 (
0!
#2820000000
0#
b1000110 "
1&
1!
#2822000000
0)
bx (
#2825000000
b0 (
0!
#2830000000
0&
b1000110 '
1!
#2832000000
bx (
#2835000000
b0 (
0!
#2840000000
1#
b1000111 $
1&
1!
#2842000000
1)
b1000111 *
bx (
#2845000000
b0 (
0!
#2850000000
0&
1!
#2852000000
bx (
#2855000000
b0 (
0!
#2860000000
0#
b1000111 "
1&
1!
#2862000000
0)
bx (
#2865000000
b0 (
0!
#2870000000
0&
b1000111 '
1!
#2872000000
bx (
#2875000000
b0 (
0!
#2880000000
1#
b1001000 $
1&
1!
#2882000000
1)
b1001000 *
bx (
#2885000000
b0 (
0!
#2890000000
0&
1!
#2892000000
bx (
#2895000000
b0 (
0!
#2900000000
0#
b1001000 "
1&
1!
#2902000000
0)
bx (
#2905000000
b0 (
0!
#2910000000
0&
b1001000 '
1!
#2912000000
bx (
#2915000000
b0 (
0!
#2920000000
1#
b1001001 $
1&
1!
#2922000000
1)
b1001001 *
bx (
#2925000000
b0 (
0!
#2930000000
0&
1!
#2932000000
bx (
#2935000000
b0 (
0!
#2940000000
0#
b1001001 "
1&
1!
#2942000000
0)
bx (
#2945000000
b0 (
0!
#2950000000
0&
b1001001 '
1!
#2952000000
bx (
#2955000000
b0 (
0!
#2960000000
1#
b1001010 $
1&
1!
#2962000000
1)
b1001010 *
bx (
#2965000000
b0 (
0!
#2970000000
0&
1!
#2972000000
bx (
#2975000000
b0 (
0!
#2980000000
0#
b1001010 "
1&
1!
#2982000000
0)
bx (
#2985000000
b0 (
0!
#2990000000
0&
b1001010 '
1!
#2992000000
bx (
#2995000000
b0 (
0!
#3000000000
1#
b1001011 $
1&
1!
#3002000000
1)
b1001011 *
bx (
#3005000000
b0 (
0!
#3010000000
0&
1!
#3012000000
bx (
#3015000000
b0 (
0!
#3020000000
0#
b1001011 "
1&
1!
#3022000000
0)
bx (
#3025000000
b0 (
0!
#3030000000
0&
b1001011 '
1!
#3032000000
bx (
#3035000000
b0 (
0!
#3040000000
1#
b1001100 $
1&
1!
#3042000000
1)
b1001100 *
bx (
#3045000000
b0 (
0!
#3050000000
0&
1!
#3052000000
bx (
#3055000000
b0 (
0!
#3060000000
0#
b1001100 "
1&
1!
#3062000000
0)
bx (
#3065000000
b0 (
0!
#3070000000
0&
b1001100 '
1!
#3072000000
bx (
#3075000000
b0 (
0!
#3080000000
1#
b1001101 $
1&
1!
#3082000000
1)
b1001101 *
bx (
#3085000000
b0 (
0!
#3090000000
0&
1!
#3092000000
bx (
#3095000000
b0 (
0!
#3100000000
0#
b1001101 "
1&
1!
#3102000000
0)
bx (
#3105000000
b0 (
0!
#3110000000
0&
b1001101 '
1!
#3112000000
bx (
#3115000000
b0 (
0!
#3120000000
1#
b1001110 $
1&
1!
#3122000000
1)
b1001110 *
bx (
#3125000000
b0 (
0!
#3130000000
0&
1!
#3132000000
bx (
#3135000000
b0 (
0!
#3140000000
0#
b1001110 "
1&
1!
#3142000000
0)
bx (
#3145000000
b0 (
0!
#3150000000
0&
b1001110 '
1!
#3152000000
bx (
#3155000000
b0 (
0!
#3160000000
1#
b1001111 $
1&
1!
#3162000000
1)
b1001111 *
bx (
